Logic/U711/U711_CHIPSET_REGISTER.v
/*
----------------------------------------------------------------------------------
--This work is shared under the Attribution-NonCommercial-ShareAlike 4.0 International (CC BY-NC-SA 4.0) License
--https://creativecommons.org/licenses/by-nc-sa/4.0/legalcode
	
--You are free to:
--Share - copy and redistribute the material in any medium or format
--Adapt - remix, transform, and build upon the material

--Under the following terms:

--Attribution - You must give appropriate credit, provide a link to the license, and indicate if changes were made. 
--You may do so in any reasonable manner, but not in any way that suggests the licensor endorses you or your use.

--NonCommercial - You may not use the material for commercial purposes.

--ShareAlike - If you remix, transform, or build upon the material, you must distribute your contributions under the 
--same license as the original.

--No additional restrictions - You may not apply legal terms or technological measures that legally restrict others 
--from doing anything the license permits.
--------------------------------------------------------------------------------------------------------------------------------------------------------------------
-- Engineer: Jason Neus
-- 
-- Design Name: U711
-- Module Name: U711_CHIPSET_REGISTER
-- Project Name: AmigaPCI
-- Target Devices: 
--
-- Description: LOGIC FOR CHIP SET REGISTER CYCLES.
--
-- Revision History:
--     13-JAN-2023 : Initial Engineering Release
----------------------------------------------------------------------------------
*/

module U711_CHIPSET_REGISTER (
    input CLK7,
    input CLK40, 
    input nRESET,
    input nREGEN,
    input RnW,
    input nDBR,

    output reg AS_EN,
    output reg LDS_EN,
    output reg UDS_EN,
    output reg REG_TA
);

//THE CHIPSET REGISTER CYCLE IS MC68000 COMPATABLE.

//7MHz CLOCK EDGE DETECTION
reg [1:0]EDGE7;
reg [2:0]EDGE_COUNT;

always @(posedge CLK40, negedge nRESET) begin
	if (!nRESET) begin
		EDGE7 <= 2'b11;
	end else begin
		EDGE7 <= {EDGE7[0], CLK7};
	end
end

////////////////////
// REGISTER CYCLE //
////////////////////

//THE CHIPSET REGISTER CYCLE CANNOT PROCEED UNTIL _DBR IS NEGATED,
//INDICATING THERE IS NOT A CHIPSET DMA CYCLE IN PROGRESS.
//IN THE EVENT _DBR IS ASSERTED, WE WAIT AT STATE 4 UNTIL
//_DBR IS NEGATED. THIS IS WHEN _DTACK WOULD NORMALLY BE ASSERTED.

always @(negedge CLK40, negedge nRESET) begin
    if (!nRESET) begin
        AS_EN <= 0;
        LDS_EN <= 0;
        UDS_EN <= 0;
        REG_TA <= 0;
        EDGE_COUNT <= 3'b000;        
    end else begin
        case (EDGE_COUNT)
            3'b000: //STATE 2
                if (!nREGEN) begin
                    AS_EN <= 1;
                    EDGE_COUNT <= 3'b001;
                    if (RnW) begin
                        LDS_EN <= 1;
                        UDS_EN <= 1;
                    end                    
                end
            
            3'b001: //STATE 3
                if (EDGE7 == 2'b01) begin EDGE_COUNT <= 3'b010; end

            3'b010: //STATE 4
                if (EDGE7 == 2'b10 && nDBR) begin 
                    LDS_EN <= 1;
                    UDS_EN <= 1;
                    EDGE_COUNT <= 3'b011;
                end

            3'b011:  //STATE 5
                if (EDGE7 == 2'b01) begin EDGE_COUNT <= 3'b100; end

            3'b100: //STATE 6
                if (EDGE7 == 2'b10) begin 
                    REG_TA <= 1; 
                    AS_EN <= 0;
                    LDS_EN <= 0;
                    UDS_EN <= 0;   
                    EDGE_COUNT <= 3'b101; 
                end

            3'b101 : //STATE 7
                begin  
                    REG_TA <= 0; 
                    if (EDGE7 == 2'b01) begin EDGE_COUNT <= 3'b000; end
                end
        endcase
    end
end
    
endmodule

Logic/U711/U711_TOP.v
/*
----------------------------------------------------------------------------------
--This work is shared under the Attribution-NonCommercial-ShareAlike 4.0 International (CC BY-NC-SA 4.0) License
--https://creativecommons.org/licenses/by-nc-sa/4.0/legalcode
	
--You are free to:
--Share - copy and redistribute the material in any medium or format
--Adapt - remix, transform, and build upon the material

--Under the following terms:

--Attribution - You must give appropriate credit, provide a link to the license, and indicate if changes were made. 
--You may do so in any reasonable manner, but not in any way that suggests the licensor endorses you or your use.

--NonCommercial - You may not use the material for commercial purposes.

--ShareAlike - If you remix, transform, or build upon the material, you must distribute your contributions under the 
--same license as the original.

--No additional restrictions - You may not apply legal terms or technological measures that legally restrict others 
--from doing anything the license permits.
--------------------------------------------------------------------------------------------------------------------------------------------------------------------
-- Engineer: Jason Neus
-- 
-- Design Name: U711
-- Module Name: U711_TOP
-- Project Name: AmigaPCI
-- Target Devices: 
--
-- Description: LOGIC FOR CHIP SET RAM CONTROLLER AND CHIPSET REGISTER CYCLES.
--
-- Revision History:
--     13-JAN-2023 : Initial Engineering Release
----------------------------------------------------------------------------------
*/

module U711_TOP (

    input CLK7,
    input CLK40, 
    input nRESET,
    input nREGEN,
    input RnW,
    input [1:0]A,
    input nDBR,
    //input nBG,

    input SIZ0,
    input SIZ1,
    //inout TT0,
    //inout TT1,

    output nLDS,
    output nUDS,
    output nAS,
    output nTA
    
);

//////////////////////////
// MC68040 TRANSFER ACK //
//////////////////////////

wire REG_TAm;
reg TA_HOLD;
reg TA_CYCLE;

assign TA = REG_TAm;
assign TA_SPACE = !nREGEN;
assign nTA = TA ? 1'b0 : TA_SPACE || TA_HOLD ? 1'b1 : 1'bZ;

//TA_HOLD FORCES _TA HIGH AFTER ASSERTION TO PREVENT IT INADVERTENTLY
//ENDING THE NEXT CYCLE PREMATURELY.
always @(posedge CLK40, negedge nRESET) begin
    if (!nRESET) begin
        TA_CYCLE <= 0;
    end else begin
        if (!nTA && TA_SPACE) begin
            TA_CYCLE <= 1; end 
        else begin
            TA_CYCLE <= 0; 
        end
    end
end

always @(negedge CLK40, negedge nRESET) begin
    if (!nRESET) begin
        TA_HOLD <= 0;
    end else begin
        TA_HOLD <= TA_CYCLE;
    end
end

//////////////////////////
// MC68000 DATA STROBES //
//////////////////////////

wire UDS_ENm;
wire LDS_ENm;
wire AS_ENm;

//GENERATE MC68000 STROBES FOR AGNUS CYCLES.
assign nAS = ~AS_ENm;
assign nUDS = ~(!A[0] && UDS_ENm);
assign nLDS = ~((SIZ1 || !SIZ0 || A[0]) && LDS_ENm);

// REGISTER CYCLE TOP

U711_CHIPSET_REGISTER U711_CHIPSET_REGISTER 
(
    .CLK7 (CLK7),
    .CLK40 (CLK40), 
    .nRESET (nRESET),
    .nREGEN (nREGEN),
    .RnW (RnW),
    .nDBR (nDBR),
    .AS_EN (AS_ENm),
    .LDS_EN (LDS_ENm),
    .UDS_EN (UDS_ENm),
    .REG_TA (REG_TAm)
);

endmodule

Logic/U711/U711_TOP_TB.v
// Define timescale <time unit> / <time precision>
`timescale 1 ns / 10 ps
`default_nettype none

//There are no ports in a test bench.
module top_tb();

//inputs
reg CLK7 = 1;
reg CLK40 = 1;
reg nRESET = 0;
reg nREGEN = 1;
reg RnW = 1;
reg [1:0]A = 2'b11;
reg SIZ0 = 1;
reg SIZ1 = 1;
reg nDBR = 1;

//outputs
wire nUDS;
wire nLDS;
wire nAS;
wire nTA;

//Simulation time : 10000 * 1ns = 10us
localparam DURATION = 10000;

//Generate Clock(s)
//7.16MHz = 139ns
//40MHz = 25ns
//80MHz = 12.5ns

always #69.5 CLK7 = ~CLK7;
always #12.5 CLK40 = ~CLK40;
//always #6.25 CLK80 = ~CLK80;

//THE TEST
initial begin
	#100 nRESET = 1;
    #135 nDBR = 0;
    #215.5 nREGEN = 0;
    #300 nDBR = 1;

end


//Test Parameters
initial begin
	$dumpfile("u711_top_tb.vcd");
	$dumpvars(0, top_tb); //0=most verbose
	//$monitor($time,,AC_ADDRESS);
	//$monitor($time,,counter);
	
	#(DURATION)
	$display("Finished");
	$finish;	
end

U711_TOP dut (

    .CLK7 (CLK7),
    .CLK40 (CLK40), 
    .nRESET (nRESET),
    .nREGEN (nREGEN),
    .RnW (RnW),
    .A (A),
    .nDBR (nDBR),
    .SIZ0 (SIZ0),
    .SIZ1 (SIZ1),    

    .nAS (nAS),
    .nLDS (nLDS),
    .nUDS (nUDS),
    .nTA (nTA)    
);

endmodule

Logic/U711/u711_top_tb.vcd
$date
	Sun Mar 10 23:19:21 2024
$end
$version
	Icarus Verilog
$end
$timescale
	1ps
$end
$scope module top_tb $end
$var wire 1 ! nUDS $end
$var wire 1 " nTA $end
$var wire 1 # nLDS $end
$var wire 1 $ nAS $end
$var reg 2 % A [1:0] $end
$var reg 1 & CLK40 $end
$var reg 1 ' CLK7 $end
$var reg 1 ( RnW $end
$var reg 1 ) SIZ0 $end
$var reg 1 * SIZ1 $end
$var reg 1 + nDBR $end
$var reg 1 , nREGEN $end
$var reg 1 - nRESET $end
$scope module dut $end
$var wire 2 . A [1:0] $end
$var wire 1 & CLK40 $end
$var wire 1 ' CLK7 $end
$var wire 1 ( RnW $end
$var wire 1 ) SIZ0 $end
$var wire 1 * SIZ1 $end
$var wire 1 / TA $end
$var wire 1 $ nAS $end
$var wire 1 + nDBR $end
$var wire 1 # nLDS $end
$var wire 1 , nREGEN $end
$var wire 1 - nRESET $end
$var wire 1 ! nUDS $end
$var wire 1 " nTA $end
$var wire 1 0 UDS_ENm $end
$var wire 1 1 TA_SPACE $end
$var wire 1 2 REG_TAm $end
$var wire 1 3 LDS_ENm $end
$var wire 1 4 AS_ENm $end
$var reg 1 5 TA_CYCLE $end
$var reg 1 6 TA_HOLD $end
$scope module U711_CHIPSET_REGISTER $end
$var wire 1 & CLK40 $end
$var wire 1 ' CLK7 $end
$var wire 1 ( RnW $end
$var wire 1 + nDBR $end
$var wire 1 , nREGEN $end
$var wire 1 - nRESET $end
$var reg 1 4 AS_EN $end
$var reg 2 7 EDGE7 [1:0] $end
$var reg 3 8 EDGE_COUNT [2:0] $end
$var reg 1 3 LDS_EN $end
$var reg 1 2 REG_TA $end
$var reg 1 0 UDS_EN $end
$upscope $end
$upscope $end
$upscope $end
$enddefinitions $end
#0
$dumpvars
b0 8
b11 7
06
05
04
03
02
01
00
0/
b11 .
0-
1,
1+
1*
1)
1(
1'
1&
b11 %
1$
1#
z"
1!
$end
#12500
0&
#25000
1&
#37500
0&
#50000
1&
#62500
0&
#69500
0'
#75000
1&
#87500
0&
#100000
b10 7
1&
1-
#112500
0&
#125000
b0 7
1&
#137500
0&
#139000
1'
#150000
b1 7
1&
#162500
0&
#175000
b11 7
1&
#187500
0&
#200000
1&
#208500
0'
#212500
0&
#225000
b10 7
1&
#235000
0+
#237500
0&
#250000
b0 7
1&
#262500
0&
#275000
1&
#278000
1'
#287500
0&
#300000
b1 7
1&
#312500
0&
#325000
b11 7
1&
#337500
0&
#347500
0'
#350000
b10 7
1&
#362500
0&
#375000
b0 7
1&
#387500
0&
#400000
1&
#412500
0&
#417000
1'
#425000
b1 7
1&
#437500
0&
#450000
b11 7
1&
#450500
1"
11
0,
#462500
0#
0$
10
13
b1 8
14
0&
#475000
1&
#486500
0'
#487500
0&
#500000
b10 7
1&
#512500
0&
#525000
b0 7
1&
#537500
0&
#550000
1&
#556000
1'
#562500
0&
#575000
b1 7
1&
#587500
b10 8
0&
#600000
b11 7
1&
#612500
0&
#625000
1&
#625500
0'
#637500
0&
#650000
b10 7
1&
#662500
0&
#675000
b0 7
1&
#687500
0&
#695000
1'
#700000
b1 7
1&
#712500
0&
#725000
b11 7
1&
#737500
0&
#750000
1&
#750500
1+
#762500
0&
#764500
0'
#775000
b10 7
1&
#787500
b11 8
0&
#800000
b0 7
1&
#812500
0&
#825000
1&
#834000
1'
#837500
0&
#850000
b1 7
1&
#862500
b100 8
0&
#875000
b11 7
1&
#887500
0&
#900000
1&
#903500
0'
#912500
0&
#925000
b10 7
1&
#937500
1#
1$
0"
b101 8
00
03
04
1/
12
0&
#950000
b0 7
15
1&
#962500
1"
16
0/
02
0&
#973000
1'
#975000
05
b1 7
1&
#987500
b0 8
06
0&
#1000000
b11 7
1&
#1012500
0#
0$
10
13
b1 8
14
0&
#1025000
1&
#1037500
0&
#1042500
0'
#1050000
b10 7
1&
#1062500
0&
#1075000
b0 7
1&
#1087500
0&
#1100000
1&
#1112000
1'
#1112500
0&
#1125000
b1 7
1&
#1137500
b10 8
0&
#1150000
b11 7
1&
#1162500
0&
#1175000
1&
#1181500
0'
#1187500
0&
#1200000
b10 7
1&
#1212500
b11 8
0&
#1225000
b0 7
1&
#1237500
0&
#1250000
1&
#1251000
1'
#1262500
0&
#1275000
b1 7
1&
#1287500
b100 8
0&
#1300000
b11 7
1&
#1312500
0&
#1320500
0'
#1325000
b10 7
1&
#1337500
1#
1$
0"
b101 8
00
03
04
1/
12
0&
#1350000
b0 7
15
1&
#1362500
1"
16
0/
02
0&
#1375000
05
1&
#1387500
06
0&
#1390000
1'
#1400000
b1 7
1&
#1412500
b0 8
0&
#1425000
b11 7
1&
#1437500
0#
0$
10
13
b1 8
14
0&
#1450000
1&
#1459500
0'
#1462500
0&
#1475000
b10 7
1&
#1487500
0&
#1500000
b0 7
1&
#1512500
0&
#1525000
1&
#1529000
1'
#1537500
0&
#1550000
b1 7
1&
#1562500
b10 8
0&
#1575000
b11 7
1&
#1587500
0&
#1598500
0'
#1600000
b10 7
1&
#1612500
b11 8
0&
#1625000
b0 7
1&
#1637500
0&
#1650000
1&
#1662500
0&
#1668000
1'
#1675000
b1 7
1&
#1687500
b100 8
0&
#1700000
b11 7
1&
#1712500
0&
#1725000
1&
#1737500
0&
0'
#1750000
b10 7
1&
#1762500
1#
1$
0"
b101 8
00
03
04
1/
12
0&
#1775000
15
b0 7
1&
#1787500
1"
0/
02
16
0&
#1800000
05
1&
#1807000
1'
#1812500
06
0&
#1825000
b1 7
1&
#1837500
b0 8
0&
#1850000
b11 7
1&
#1862500
0#
0$
10
13
b1 8
14
0&
#1875000
1&
#1876500
0'
#1887500
0&
#1900000
b10 7
1&
#1912500
0&
#1925000
b0 7
1&
#1937500
0&
#1946000
1'
#1950000
b1 7
1&
#1962500
b10 8
0&
#1975000
b11 7
1&
#1987500
0&
#2000000
1&
#2012500
0&
#2015500
0'
#2025000
b10 7
1&
#2037500
b11 8
0&
#2050000
b0 7
1&
#2062500
0&
#2075000
1&
#2085000
1'
#2087500
0&
#2100000
b1 7
1&
#2112500
b100 8
0&
#2125000
b11 7
1&
#2137500
0&
#2150000
1&
#2154500
0'
#2162500
0&
#2175000
b10 7
1&
#2187500
1#
1$
0"
b101 8
00
03
04
1/
12
0&
#2200000
b0 7
15
1&
#2212500
1"
16
0/
02
0&
#2224000
1'
#2225000
05
b1 7
1&
#2237500
b0 8
06
0&
#2250000
b11 7
1&
#2262500
0#
0$
10
13
b1 8
14
0&
#2275000
1&
#2287500
0&
#2293500
0'
#2300000
b10 7
1&
#2312500
0&
#2325000
b0 7
1&
#2337500
0&
#2350000
1&
#2362500
0&
#2363000
1'
#2375000
b1 7
1&
#2387500
b10 8
0&
#2400000
b11 7
1&
#2412500
0&
#2425000
1&
#2432500
0'
#2437500
0&
#2450000
b10 7
1&
#2462500
b11 8
0&
#2475000
b0 7
1&
#2487500
0&
#2500000
1&
#2502000
1'
#2512500
0&
#2525000
b1 7
1&
#2537500
b100 8
0&
#2550000
b11 7
1&
#2562500
0&
#2571500
0'
#2575000
b10 7
1&
#2587500
1#
1$
0"
b101 8
00
03
04
1/
12
0&
#2600000
b0 7
15
1&
#2612500
1"
16
0/
02
0&
#2625000
05
1&
#2637500
06
0&
#2641000
1'
#2650000
b1 7
1&
#2662500
b0 8
0&
#2675000
b11 7
1&
#2687500
0#
0$
10
13
b1 8
14
0&
#2700000
1&
#2710500
0'
#2712500
0&
#2725000
b10 7
1&
#2737500
0&
#2750000
b0 7
1&
#2762500
0&
#2775000
1&
#2780000
1'
#2787500
0&
#2800000
b1 7
1&
#2812500
b10 8
0&
#2825000
b11 7
1&
#2837500
0&
#2849500
0'
#2850000
b10 7
1&
#2862500
b11 8
0&
#2875000
b0 7
1&
#2887500
0&
#2900000
1&
#2912500
0&
#2919000
1'
#2925000
b1 7
1&
#2937500
b100 8
0&
#2950000
b11 7
1&
#2962500
0&
#2975000
1&
#2987500
0&
#2988500
0'
#3000000
b10 7
1&
#3012500
1#
1$
0"
b101 8
00
03
04
1/
12
0&
#3025000
15
b0 7
1&
#3037500
1"
0/
02
16
0&
#3050000
05
1&
#3058000
1'
#3062500
06
0&
#3075000
b1 7
1&
#3087500
b0 8
0&
#3100000
b11 7
1&
#3112500
0#
0$
10
13
b1 8
14
0&
#3125000
1&
#3127500
0'
#3137500
0&
#3150000
b10 7
1&
#3162500
0&
#3175000
b0 7
1&
#3187500
0&
#3197000
1'
#3200000
b1 7
1&
#3212500
b10 8
0&
#3225000
b11 7
1&
#3237500
0&
#3250000
1&
#3262500
0&
#3266500
0'
#3275000
b10 7
1&
#3287500
b11 8
0&
#3300000
b0 7
1&
#3312500
0&
#3325000
1&
#3336000
1'
#3337500
0&
#3350000
b1 7
1&
#3362500
b100 8
0&
#3375000
b11 7
1&
#3387500
0&
#3400000
1&
#3405500
0'
#3412500
0&
#3425000
b10 7
1&
#3437500
1#
1$
0"
b101 8
00
03
04
1/
12
0&
#3450000
b0 7
15
1&
#3462500
1"
16
0/
02
0&
#3475000
05
b1 7
1&
1'
#3487500
b0 8
06
0&
#3500000
b11 7
1&
#3512500
0#
0$
10
13
b1 8
14
0&
#3525000
1&
#3537500
0&
#3544500
0'
#3550000
b10 7
1&
#3562500
0&
#3575000
b0 7
1&
#3587500
0&
#3600000
1&
#3612500
0&
#3614000
1'
#3625000
b1 7
1&
#3637500
b10 8
0&
#3650000
b11 7
1&
#3662500
0&
#3675000
1&
#3683500
0'
#3687500
0&
#3700000
b10 7
1&
#3712500
b11 8
0&
#3725000
b0 7
1&
#3737500
0&
#3750000
1&
#3753000
1'
#3762500
0&
#3775000
b1 7
1&
#3787500
b100 8
0&
#3800000
b11 7
1&
#3812500
0&
#3822500
0'
#3825000
b10 7
1&
#3837500
1#
1$
0"
b101 8
00
03
04
1/
12
0&
#3850000
b0 7
15
1&
#3862500
1"
16
0/
02
0&
#3875000
05
1&
#3887500
06
0&
#3892000
1'
#3900000
b1 7
1&
#3912500
b0 8
0&
#3925000
b11 7
1&
#3937500
0#
0$
10
13
b1 8
14
0&
#3950000
1&
#3961500
0'
#3962500
0&
#3975000
b10 7
1&
#3987500
0&
#4000000
b0 7
1&
#4012500
0&
#4025000
1&
#4031000
1'
#4037500
0&
#4050000
b1 7
1&
#4062500
b10 8
0&
#4075000
b11 7
1&
#4087500
0&
#4100000
1&
#4100500
0'
#4112500
0&
#4125000
b10 7
1&
#4137500
b11 8
0&
#4150000
b0 7
1&
#4162500
0&
#4170000
1'
#4175000
b1 7
1&
#4187500
b100 8
0&
#4200000
b11 7
1&
#4212500
0&
#4225000
1&
#4237500
0&
#4239500
0'
#4250000
b10 7
1&
#4262500
1#
1$
0"
b101 8
00
03
04
1/
12
0&
#4275000
15
b0 7
1&
#4287500
1"
0/
02
16
0&
#4300000
05
1&
#4309000
1'
#4312500
06
0&
#4325000
b1 7
1&
#4337500
b0 8
0&
#4350000
b11 7
1&
#4362500
0#
0$
10
13
b1 8
14
0&
#4375000
1&
#4378500
0'
#4387500
0&
#4400000
b10 7
1&
#4412500
0&
#4425000
b0 7
1&
#4437500
0&
#4448000
1'
#4450000
b1 7
1&
#4462500
b10 8
0&
#4475000
b11 7
1&
#4487500
0&
#4500000
1&
#4512500
0&
#4517500
0'
#4525000
b10 7
1&
#4537500
b11 8
0&
#4550000
b0 7
1&
#4562500
0&
#4575000
1&
#4587000
1'
#4587500
0&
#4600000
b1 7
1&
#4612500
b100 8
0&
#4625000
b11 7
1&
#4637500
0&
#4650000
1&
#4656500
0'
#4662500
0&
#4675000
b10 7
1&
#4687500
1#
1$
0"
b101 8
00
03
04
1/
12
0&
#4700000
b0 7
15
1&
#4712500
1"
16
0/
02
0&
#4725000
05
1&
#4726000
1'
#4737500
06
0&
#4750000
b1 7
1&
#4762500
b0 8
0&
#4775000
b11 7
1&
#4787500
0#
0$
10
13
b1 8
14
0&
#4795500
0'
#4800000
b10 7
1&
#4812500
0&
#4825000
b0 7
1&
#4837500
0&
#4850000
1&
#4862500
0&
#4865000
1'
#4875000
b1 7
1&
#4887500
b10 8
0&
#4900000
b11 7
1&
#4912500
0&
#4925000
1&
#4934500
0'
#4937500
0&
#4950000
b10 7
1&
#4962500
b11 8
0&
#4975000
b0 7
1&
#4987500
0&
#5000000
1&
#5004000
1'
#5012500
0&
#5025000
b1 7
1&
#5037500
b100 8
0&
#5050000
b11 7
1&
#5062500
0&
#5073500
0'
#5075000
b10 7
1&
#5087500
1#
1$
0"
b101 8
00
03
04
1/
12
0&
#5100000
b0 7
15
1&
#5112500
1"
16
0/
02
0&
#5125000
05
1&
#5137500
06
0&
#5143000
1'
#5150000
b1 7
1&
#5162500
b0 8
0&
#5175000
b11 7
1&
#5187500
0#
0$
10
13
b1 8
14
0&
#5200000
1&
#5212500
0&
0'
#5225000
b10 7
1&
#5237500
0&
#5250000
b0 7
1&
#5262500
0&
#5275000
1&
#5282000
1'
#5287500
0&
#5300000
b1 7
1&
#5312500
b10 8
0&
#5325000
b11 7
1&
#5337500
0&
#5350000
1&
#5351500
0'
#5362500
0&
#5375000
b10 7
1&
#5387500
b11 8
0&
#5400000
b0 7
1&
#5412500
0&
#5421000
1'
#5425000
b1 7
1&
#5437500
b100 8
0&
#5450000
b11 7
1&
#5462500
0&
#5475000
1&
#5487500
0&
#5490500
0'
#5500000
b10 7
1&
#5512500
1#
1$
0"
b101 8
00
03
04
1/
12
0&
#5525000
15
b0 7
1&
#5537500
1"
0/
02
16
0&
#5550000
05
1&
#5560000
1'
#5562500
06
0&
#5575000
b1 7
1&
#5587500
b0 8
0&
#5600000
b11 7
1&
#5612500
0#
0$
10
13
b1 8
14
0&
#5625000
1&
#5629500
0'
#5637500
0&
#5650000
b10 7
1&
#5662500
0&
#5675000
b0 7
1&
#5687500
0&
#5699000
1'
#5700000
b1 7
1&
#5712500
b10 8
0&
#5725000
b11 7
1&
#5737500
0&
#5750000
1&
#5762500
0&
#5768500
0'
#5775000
b10 7
1&
#5787500
b11 8
0&
#5800000
b0 7
1&
#5812500
0&
#5825000
1&
#5837500
0&
#5838000
1'
#5850000
b1 7
1&
#5862500
b100 8
0&
#5875000
b11 7
1&
#5887500
0&
#5900000
1&
#5907500
0'
#5912500
0&
#5925000
b10 7
1&
#5937500
1#
1$
0"
b101 8
00
03
04
1/
12
0&
#5950000
b0 7
15
1&
#5962500
1"
16
0/
02
0&
#5975000
05
1&
#5977000
1'
#5987500
06
0&
#6000000
b1 7
1&
#6012500
b0 8
0&
#6025000
b11 7
1&
#6037500
0#
0$
10
13
b1 8
14
0&
#6046500
0'
#6050000
b10 7
1&
#6062500
0&
#6075000
b0 7
1&
#6087500
0&
#6100000
1&
#6112500
0&
#6116000
1'
#6125000
b1 7
1&
#6137500
b10 8
0&
#6150000
b11 7
1&
#6162500
0&
#6175000
1&
#6185500
0'
#6187500
0&
#6200000
b10 7
1&
#6212500
b11 8
0&
#6225000
b0 7
1&
#6237500
0&
#6250000
1&
#6255000
1'
#6262500
0&
#6275000
b1 7
1&
#6287500
b100 8
0&
#6300000
b11 7
1&
#6312500
0&
#6324500
0'
#6325000
b10 7
1&
#6337500
1#
1$
0"
b101 8
00
03
04
1/
12
0&
#6350000
b0 7
15
1&
#6362500
1"
16
0/
02
0&
#6375000
05
1&
#6387500
06
0&
#6394000
1'
#6400000
b1 7
1&
#6412500
b0 8
0&
#6425000
b11 7
1&
#6437500
0#
0$
10
13
b1 8
14
0&
#6450000
1&
#6462500
0&
#6463500
0'
#6475000
b10 7
1&
#6487500
0&
#6500000
b0 7
1&
#6512500
0&
#6525000
1&
#6533000
1'
#6537500
0&
#6550000
b1 7
1&
#6562500
b10 8
0&
#6575000
b11 7
1&
#6587500
0&
#6600000
1&
#6602500
0'
#6612500
0&
#6625000
b10 7
1&
#6637500
b11 8
0&
#6650000
b0 7
1&
#6662500
0&
#6672000
1'
#6675000
b1 7
1&
#6687500
b100 8
0&
#6700000
b11 7
1&
#6712500
0&
#6725000
1&
#6737500
0&
#6741500
0'
#6750000
b10 7
1&
#6762500
1#
1$
0"
b101 8
00
03
04
1/
12
0&
#6775000
15
b0 7
1&
#6787500
1"
0/
02
16
0&
#6800000
05
1&
#6811000
1'
#6812500
06
0&
#6825000
b1 7
1&
#6837500
b0 8
0&
#6850000
b11 7
1&
#6862500
0#
0$
10
13
b1 8
14
0&
#6875000
1&
#6880500
0'
#6887500
0&
#6900000
b10 7
1&
#6912500
0&
#6925000
b0 7
1&
#6937500
0&
#6950000
b1 7
1&
1'
#6962500
b10 8
0&
#6975000
b11 7
1&
#6987500
0&
#7000000
1&
#7012500
0&
#7019500
0'
#7025000
b10 7
1&
#7037500
b11 8
0&
#7050000
b0 7
1&
#7062500
0&
#7075000
1&
#7087500
0&
#7089000
1'
#7100000
b1 7
1&
#7112500
b100 8
0&
#7125000
b11 7
1&
#7137500
0&
#7150000
1&
#7158500
0'
#7162500
0&
#7175000
b10 7
1&
#7187500
1#
1$
0"
b101 8
00
03
04
1/
12
0&
#7200000
b0 7
15
1&
#7212500
1"
16
0/
02
0&
#7225000
05
1&
#7228000
1'
#7237500
06
0&
#7250000
b1 7
1&
#7262500
b0 8
0&
#7275000
b11 7
1&
#7287500
0#
0$
10
13
b1 8
14
0&
#7297500
0'
#7300000
b10 7
1&
#7312500
0&
#7325000
b0 7
1&
#7337500
0&
#7350000
1&
#7362500
0&
#7367000
1'
#7375000
b1 7
1&
#7387500
b10 8
0&
#7400000
b11 7
1&
#7412500
0&
#7425000
1&
#7436500
0'
#7437500
0&
#7450000
b10 7
1&
#7462500
b11 8
0&
#7475000
b0 7
1&
#7487500
0&
#7500000
1&
#7506000
1'
#7512500
0&
#7525000
b1 7
1&
#7537500
b100 8
0&
#7550000
b11 7
1&
#7562500
0&
#7575000
1&
#7575500
0'
#7587500
0&
#7600000
b10 7
1&
#7612500
1#
1$
0"
b101 8
00
03
04
1/
12
0&
#7625000
15
b0 7
1&
#7637500
1"
0/
02
16
0&
#7645000
1'
#7650000
b1 7
05
1&
#7662500
06
b0 8
0&
#7675000
b11 7
1&
#7687500
0#
0$
10
13
b1 8
14
0&
#7700000
1&
#7712500
0&
#7714500
0'
#7725000
b10 7
1&
#7737500
0&
#7750000
b0 7
1&
#7762500
0&
#7775000
1&
#7784000
1'
#7787500
0&
#7800000
b1 7
1&
#7812500
b10 8
0&
#7825000
b11 7
1&
#7837500
0&
#7850000
1&
#7853500
0'
#7862500
0&
#7875000
b10 7
1&
#7887500
b11 8
0&
#7900000
b0 7
1&
#7912500
0&
#7923000
1'
#7925000
b1 7
1&
#7937500
b100 8
0&
#7950000
b11 7
1&
#7962500
0&
#7975000
1&
#7987500
0&
#7992500
0'
#8000000
b10 7
1&
#8012500
1#
1$
0"
b101 8
00
03
04
1/
12
0&
#8025000
15
b0 7
1&
#8037500
1"
0/
02
16
0&
#8050000
05
1&
#8062000
1'
#8062500
06
0&
#8075000
b1 7
1&
#8087500
b0 8
0&
#8100000
b11 7
1&
#8112500
0#
0$
10
13
b1 8
14
0&
#8125000
1&
#8131500
0'
#8137500
0&
#8150000
b10 7
1&
#8162500
0&
#8175000
b0 7
1&
#8187500
0&
#8200000
1&
#8201000
1'
#8212500
0&
#8225000
b1 7
1&
#8237500
b10 8
0&
#8250000
b11 7
1&
#8262500
0&
#8270500
0'
#8275000
b10 7
1&
#8287500
b11 8
0&
#8300000
b0 7
1&
#8312500
0&
#8325000
1&
#8337500
0&
#8340000
1'
#8350000
b1 7
1&
#8362500
b100 8
0&
#8375000
b11 7
1&
#8387500
0&
#8400000
1&
#8409500
0'
#8412500
0&
#8425000
b10 7
1&
#8437500
1#
1$
0"
b101 8
00
03
04
1/
12
0&
#8450000
b0 7
15
1&
#8462500
1"
16
0/
02
0&
#8475000
05
1&
#8479000
1'
#8487500
06
0&
#8500000
b1 7
1&
#8512500
b0 8
0&
#8525000
b11 7
1&
#8537500
0#
0$
10
13
b1 8
14
0&
#8548500
0'
#8550000
b10 7
1&
#8562500
0&
#8575000
b0 7
1&
#8587500
0&
#8600000
1&
#8612500
0&
#8618000
1'
#8625000
b1 7
1&
#8637500
b10 8
0&
#8650000
b11 7
1&
#8662500
0&
#8675000
1&
#8687500
0&
0'
#8700000
b10 7
1&
#8712500
b11 8
0&
#8725000
b0 7
1&
#8737500
0&
#8750000
1&
#8757000
1'
#8762500
0&
#8775000
b1 7
1&
#8787500
b100 8
0&
#8800000
b11 7
1&
#8812500
0&
#8825000
1&
#8826500
0'
#8837500
0&
#8850000
b10 7
1&
#8862500
1#
1$
0"
b101 8
00
03
04
1/
12
0&
#8875000
15
b0 7
1&
#8887500
1"
0/
02
16
0&
#8896000
1'
#8900000
b1 7
05
1&
#8912500
06
b0 8
0&
#8925000
b11 7
1&
#8937500
0#
0$
10
13
b1 8
14
0&
#8950000
1&
#8962500
0&
#8965500
0'
#8975000
b10 7
1&
#8987500
0&
#9000000
b0 7
1&
#9012500
0&
#9025000
1&
#9035000
1'
#9037500
0&
#9050000
b1 7
1&
#9062500
b10 8
0&
#9075000
b11 7
1&
#9087500
0&
#9100000
1&
#9104500
0'
#9112500
0&
#9125000
b10 7
1&
#9137500
b11 8
0&
#9150000
b0 7
1&
#9162500
0&
#9174000
1'
#9175000
b1 7
1&
#9187500
b100 8
0&
#9200000
b11 7
1&
#9212500
0&
#9225000
1&
#9237500
0&
#9243500
0'
#9250000
b10 7
1&
#9262500
1#
1$
0"
b101 8
00
03
04
1/
12
0&
#9275000
15
b0 7
1&
#9287500
1"
0/
02
16
0&
#9300000
05
1&
#9312500
06
0&
#9313000
1'
#9325000
b1 7
1&
#9337500
b0 8
0&
#9350000
b11 7
1&
#9362500
0#
0$
10
13
b1 8
14
0&
#9375000
1&
#9382500
0'
#9387500
0&
#9400000
b10 7
1&
#9412500
0&
#9425000
b0 7
1&
#9437500
0&
#9450000
1&
#9452000
1'
#9462500
0&
#9475000
b1 7
1&
