Logic/U409/U409_AUTOCONFIG.v
/*
----------------------------------------------------------------------------------
--This work is shared under the Attribution-NonCommercial-ShareAlike 4.0 International (CC BY-NC-SA 4.0) License
--https://creativecommons.org/licenses/by-nc-sa/4.0/legalcode
	
--You are free to:
--Share - copy and redistribute the material in any medium or format
--Adapt - remix, transform, and build upon the material

--Under the following terms:

--Attribution - You must give appropriate credit, provide a link to the license, and indicate if changes were made. 
--You may do so in any reasonable manner, but not in any way that suggests the licensor endorses you or your use.

--NonCommercial - You may not use the material for commercial purposes.

--ShareAlike - If you remix, transform, or build upon the material, you must distribute your contributions under the 
--same license as the original.

--No additional restrictions - You may not apply legal terms or technological measures that legally restrict others 
--from doing anything the license permits.
--------------------------------------------------------------------------------------------------------------------------------------------------------------------
-- Engineer: Jason Neus
-- 
-- Design Name: U409
-- Module Name: Onboard AUTOCONFIG
-- Project Name: AmigaPCI
-- Target Devices: XC95144XL 144 PIN
--
-- Description: LOGIC FOR CONFIGURATION OF ONBOARD RESOURCES: IDE, ZORRO 3 RAM, AND THE PCI BRIDGE.
--
-- Revision History:
--     05-JAN-2023 : Initial Engineering Release.
--     29-FEB-2024 : Rewrite for iCE FPGA.
----------------------------------------------------------------------------------
*/

module U409_AUTOCONFIG
(

    input CLK40,
    input [31:1] A,
    input nTS,
    input AUTOCONFIG_SPACE,
    input AUTOBOOT,
    input nRESET,
    input RnW,
    input nTIP,
    input [3:0] DIN,

    output reg [3:0] DOUT,
    output wire CONFIGED,		
    output reg [3:0] RAM_BASE_ADDRESS,
    output reg [2:0] PCI_BRIDGE_BASE_ADDRESS,	 
    output wire IDE_ACCESS,
    output reg IDE_ENABLE,
    output reg nAC_TA

);

reg [2:0] IDE_BASE_ADDRESS;
reg RAM_CONFIGURED;
reg IDE_CONFIGURED;
reg BRIDGE_CONFIGURED;
	
/////////////////////
// DISABLE IDE ROM //
/////////////////////

//ON THE FIRST WRITE TO THE IDE ADDRESS SPACE, WE DISABLE ROM ACCESS.

assign IDE_ACCESS = A[23:20] == 4'hE && A[19:17] == IDE_BASE_ADDRESS && CONFIGED;

always @(negedge nTS or negedge nRESET) begin    
    if (!nRESET) begin
        IDE_ENABLE <= 0;
    end else begin
        if (!IDE_ENABLE) begin
            IDE_ENABLE <= (IDE_ACCESS && !RnW);
        end
    end
end

///////////////////////
// CONFIGURED SIGNAL //
///////////////////////

//ARE ALL THE ON-BOARD RESOURCES CONFIGURED?
assign CONFIGED = RAM_CONFIGURED && (IDE_CONFIGURED || !AUTOBOOT) && BRIDGE_CONFIGURED;

//////////////////////
// AUTOCONFIG CYCLE //
//////////////////////

//reg [3:0] DOUT;
//assign AC_DOUT = AUTOCONFIG_SPACE ? DOUT : 4'bz;

//wire [7:0] AC_ADDRESS;
//assign AC_ADDRESS = {A[7:2], A[8], 1'b0};

wire [7:0] AC_ADDRESS;
assign AC_ADDRESS = {A[7:1], 1'b0};

always @(posedge CLK40 or negedge nRESET) begin

    if (!nRESET) begin       

        IDE_BASE_ADDRESS <= 3'h0;
        RAM_BASE_ADDRESS <= 4'h0;
        PCI_BRIDGE_BASE_ADDRESS <= 3'h0;        
        RAM_CONFIGURED <= 0;
        IDE_CONFIGURED <= 0;
        BRIDGE_CONFIGURED <= 0;
        DOUT <= 4'h0;        

    end else if (AUTOCONFIG_SPACE && !CONFIGED) begin

        if (RnW && !nTS) begin

            //REGISTER READ CYCLE            

            case (AC_ADDRESS)

                8'h0 : if (!BRIDGE_CONFIGURED) begin DOUT <= 4'b1000; end else if (!RAM_CONFIGURED) begin DOUT <= 4'b1010; end else DOUT <= {4'b100, AUTOBOOT};
                8'h2 : if (!BRIDGE_CONFIGURED) begin DOUT <= 4'b0101; end else if (!RAM_CONFIGURED) begin DOUT <= 4'b0100; end else DOUT <= 4'b0010;
                8'h6 : if (!BRIDGE_CONFIGURED) begin DOUT <= ~4'b0011; end else if (!RAM_CONFIGURED) begin DOUT <= ~4'b0100; end else DOUT <= ~4'b0101;
                8'h8 : if (!BRIDGE_CONFIGURED) begin DOUT <= ~4'b0011; end else if (!RAM_CONFIGURED) begin DOUT <= ~4'b1110; end else DOUT <= ~4'b0000;
                8'hA : if (!BRIDGE_CONFIGURED) begin DOUT <= ~4'b0000; end else if (!RAM_CONFIGURED) begin DOUT <= ~4'b0001; end else DOUT <= ~4'b0000;
                8'h12 : if (!BRIDGE_CONFIGURED) begin DOUT <= ~4'b0010; end else if (!RAM_CONFIGURED) begin DOUT <= ~4'b0010; end else DOUT <= ~4'b0010;
                8'h14 : if (!BRIDGE_CONFIGURED) begin DOUT <= ~4'b0101; end else if (!RAM_CONFIGURED) begin DOUT <= ~4'b0101; end else DOUT <= ~4'b0101;
                8'h16 : if (!BRIDGE_CONFIGURED) begin DOUT <= ~4'b1000; end else if (!RAM_CONFIGURED) begin DOUT <= ~4'b1000; end else DOUT <= ~4'b1000;
                //8'h28 : if (!BRIDGE_CONFIGURED) begin DOUT <= ~4'b0000; end else if (!RAM_CONFIGURED) begin DOUT <= ~4'b0000; end else DOUT <= ~4'b1000;
                //8'h2E : if (!BRIDGE_CONFIGURED) begin DOUT <= ~4'b0000; end else if (!RAM_CONFIGURED) begin DOUT <= ~4'b0000; end else DOUT <= ~4'b0100;
                default : DOUT <= ~4'h0;

            endcase
        
        end else if (!RnW && nTS && !nTIP) begin
        
            //REGISTER WRITE CYCLE
            //DATA IS NOT VALID UNTIL THE RISING EDGE OF CLOCK 2 OF A WRITE CYCLE.
            //WAITING FOR _TS TO NEGATE WHILE _TIP IS ASSERTED GETS US TO THE SECOND CLOCK.

            if (AC_ADDRESS == 8'h44 && RAM_CONFIGURED && BRIDGE_CONFIGURED) begin
                IDE_BASE_ADDRESS <= DIN[3:1];                
            end else if (AC_ADDRESS == 8'h48) begin
                if (!BRIDGE_CONFIGURED) begin
                    PCI_BRIDGE_BASE_ADDRESS <= DIN[3:1];
                    BRIDGE_CONFIGURED <= 1;
                end else if (!RAM_CONFIGURED) begin
                    RAM_BASE_ADDRESS <= DIN[3:0];
                    RAM_CONFIGURED <= 1;
                end else begin
                    IDE_CONFIGURED <= 1;
                end 
            end
        end
    end
end

////////////////////
// AUTOCONFIG ACK //
////////////////////

always @(negedge CLK40 or negedge nRESET) begin
    if (!nRESET) begin
        nAC_TA <= 1;
    end else if (AUTOCONFIG_SPACE && nTS && !nTIP) begin
        nAC_TA <= ~nAC_TA;
    end else begin
        nAC_TA <= 1;
    end
end

endmodule

Logic/TestBenches/U409-TESTBENCH/AUTOCONFIG/U409_AUTOCONFIG_tb.v
// Define timescale <time unit> / <time precision>
`timescale 1 ns / 10 ps
`default_nettype none

//There are no ports in a test bench.
module autoconfig_tb();

//reg inputs
reg CLK40 = 1;
reg RnW = 1;
reg nTIP = 1;
reg nRESET = 0;
reg [31:1] A = 'h0;
reg nTS = 1;
reg AUTOCONFIG_SPACE = 0;
reg AUTOBOOT = 1;
reg [31:28] DIN = 'h0;

wire [31:28] DOUT;
wire CONFIGED;
wire [3:0] RAM_BASE_ADDRESS;
wire [2:0] PCI_BRIDGE_BASE_ADDRESS;
wire [2:0] IDE_BASE_ADDRESS;
wire IDE_ACCESS;
wire IDE_ENABLE;
wire nAC_TA;

reg [1:0] i;

//Simulation time : 10000 * 1ns = 10us
localparam DURATION = 10000;

//Generate Clock(s)
//7.16MHz = 139ns
//40MHz = 25ns
//80MHz = 12.5ns

always #12.5 CLK40 = ~CLK40;

//THE TEST
initial begin
	#100 nRESET = 1;
    #187.5 
    //AUTOCONFIG
    for (i = 0; i < 3; i = i + 1) begin
        #100 AUTOCONFIG_SPACE = 1; nTS = 0; nTIP = 0; A = 31'b000000000000000000000000000000;
        #25 nTS = 1;
        #25 nTS = 0; A = 31'b1111111100000000000000000000001; //02
        #25 nTS = 1;
        #25 nTS = 0; A = 31'b1111111100000000000000000000011; //06
        #25 nTS = 1;
        #25 nTS = 0; A = 31'b1111111100000000000000000000100; //08
        #25 nTS = 1;
        #25 nTS = 0; A = 31'b1111111100000000000000000000101; //0A
        #25 nTS = 1;
        #25 nTS = 0; A = 31'b1111111100000000000000000001001; //12
        #25 nTS = 1;
        #25 nTS = 0; A = 31'b1111111100000000000000000001010; //14
        #25 nTS = 1;
        #25 nTS = 0; A = 31'b1111111100000000000000000001011; //16
        #25 nTS = 1; RnW = 0;
        #25 nTS = 0; 
            A = 31'b1111111100000000000000000100010; //44
            DIN = 4'b1000 + i;
        #25 nTS = 1;
        #25 nTS = 0; A = 31'b1111111100000000000000000100100; //48
        #25 nTS = 1; 
        #25 RnW = 1; nTIP = 1; AUTOCONFIG_SPACE = 0;
    end
    //IDE ACCESS
    #100 nTS = 0; nTIP = 0; A = 31'b0000000011101010000000000000000;
    #25 nTS = 1; #100 nTIP = 1;
    #100 nTS = 0; nTIP = 0; RnW = 0;
    #25 nTS = 1; #100 nTIP = 1; RnW = 1; A = 31'b000000000000000000000000000000;
    
end

//Test Parameters
initial begin
	$dumpfile("autoconfig_tb.vcd");
	$dumpvars(0, autoconfig_tb); //0=most verbose
	//$monitor($time,,AC_ADDRESS);
	//$monitor($time,,counter);
	
	#(DURATION)
	$display("Finished");
	$finish;	
end

//Instantiate the device under test
U409_AUTOCONFIG dut
(
    .CLK40 (CLK40),
    .A (A[31:1]),
    .nTS (nTS),
    .AUTOCONFIG_SPACE (AUTOCONFIG_SPACE),
    .AUTOBOOT (AUTOBOOT),
    .nRESET (nRESET),
    .RnW (RnW),
    .nTIP (nTIP),
    .DIN (DIN),
    .DOUT (DOUT),
    .CONFIGED (CONFIGED),		
    .RAM_BASE_ADDRESS (RAM_BASE_ADDRESS),
    .PCI_BRIDGE_BASE_ADDRESS (PCI_BRIDGE_BASE_ADDRESS),	 
    .IDE_ACCESS (IDE_ACCESS),
    .IDE_ENABLE (IDE_ENABLE),
    .nAC_TA (nAC_TA)
);

endmodule

Logic/TestBenches/U409-TESTBENCH/AUTOCONFIG/autoconfig_tb.vcd
$date
	Sat Mar  2 16:26:47 2024
$end
$version
	Icarus Verilog
$end
$timescale
	1ps
$end
$scope module autoconfig_tb $end
$var wire 1 ! nAC_TA $end
$var wire 4 " RAM_BASE_ADDRESS [3:0] $end
$var wire 3 # PCI_BRIDGE_BASE_ADDRESS [2:0] $end
$var wire 1 $ IDE_ENABLE $end
$var wire 1 % IDE_ACCESS $end
$var wire 4 & DOUT [31:28] $end
$var wire 1 ' CONFIGED $end
$var reg 31 ( A [31:1] $end
$var reg 1 ) AUTOBOOT $end
$var reg 1 * AUTOCONFIG_SPACE $end
$var reg 1 + CLK40 $end
$var reg 4 , DIN [31:28] $end
$var reg 1 - RnW $end
$var reg 2 . i [1:0] $end
$var reg 1 / nRESET $end
$var reg 1 0 nTIP $end
$var reg 1 1 nTS $end
$scope module dut $end
$var wire 31 2 A [31:1] $end
$var wire 1 ) AUTOBOOT $end
$var wire 1 * AUTOCONFIG_SPACE $end
$var wire 1 + CLK40 $end
$var wire 1 ' CONFIGED $end
$var wire 4 3 DIN [3:0] $end
$var wire 1 % IDE_ACCESS $end
$var wire 1 - RnW $end
$var wire 1 / nRESET $end
$var wire 1 0 nTIP $end
$var wire 1 1 nTS $end
$var wire 8 4 AC_ADDRESS [7:0] $end
$var reg 1 5 BRIDGE_CONFIGURED $end
$var reg 4 6 DOUT [3:0] $end
$var reg 3 7 IDE_BASE_ADDRESS [2:0] $end
$var reg 1 8 IDE_CONFIGURED $end
$var reg 1 $ IDE_ENABLE $end
$var reg 3 9 PCI_BRIDGE_BASE_ADDRESS [2:0] $end
$var reg 4 : RAM_BASE_ADDRESS [3:0] $end
$var reg 1 ; RAM_CONFIGURED $end
$var reg 1 ! nAC_TA $end
$upscope $end
$upscope $end
$enddefinitions $end
#0
$dumpvars
0;
b0 :
b0 9
08
b0 7
b0 6
05
b0 4
b0 3
b0 2
11
10
0/
bx .
1-
b0 ,
1+
0*
1)
b0 (
0'
b0 &
0%
0$
b0 #
b0 "
1!
$end
#12500
0+
#25000
1+
#37500
0+
#50000
1+
#62500
0+
#75000
1+
#87500
0+
#100000
1+
1/
#112500
0+
#125000
1+
#137500
0+
#150000
1+
#162500
0+
#175000
1+
#187500
0+
#200000
1+
#212500
0+
#225000
1+
#237500
0+
#250000
1+
#262500
0+
#275000
1+
#287500
0+
b0 .
#300000
1+
#312500
0+
#325000
1+
#337500
0+
#350000
1+
#362500
0+
#375000
1+
#387500
0+
00
01
1*
#400000
b1000 &
b1000 6
1+
#412500
0!
0+
11
#425000
1+
#437500
1!
b10 4
0+
b1111111100000000000000000000001 (
b1111111100000000000000000000001 2
01
#450000
b101 &
b101 6
1+
#462500
0!
0+
11
#475000
1+
#487500
1!
b110 4
0+
b1111111100000000000000000000011 (
b1111111100000000000000000000011 2
01
#500000
b1100 &
b1100 6
1+
#512500
0!
0+
11
#525000
1+
#537500
1!
b1000 4
0+
b1111111100000000000000000000100 (
b1111111100000000000000000000100 2
01
#550000
1+
#562500
0!
0+
11
#575000
1+
#587500
1!
b1010 4
0+
b1111111100000000000000000000101 (
b1111111100000000000000000000101 2
01
#600000
b1111 &
b1111 6
1+
#612500
0!
0+
11
#625000
1+
#637500
1!
b10010 4
0+
b1111111100000000000000000001001 (
b1111111100000000000000000001001 2
01
#650000
b1101 &
b1101 6
1+
#662500
0!
0+
11
#675000
1+
#687500
1!
b10100 4
0+
b1111111100000000000000000001010 (
b1111111100000000000000000001010 2
01
#700000
b1010 &
b1010 6
1+
#712500
0!
0+
11
#725000
1+
#737500
1!
b10110 4
0+
b1111111100000000000000000001011 (
b1111111100000000000000000001011 2
01
#750000
b111 &
b111 6
1+
#762500
0!
0+
0-
11
#775000
1+
#787500
1!
b1000100 4
0+
b1000 ,
b1000 3
b1111111100000000000000000100010 (
b1111111100000000000000000100010 2
01
#800000
1+
#812500
0!
0+
11
#825000
1+
#837500
1!
b1001000 4
0+
b1111111100000000000000000100100 (
b1111111100000000000000000100100 2
01
#850000
1+
#862500
0!
0+
11
#875000
15
b100 #
b100 9
1+
#887500
1!
0+
b1 .
0*
10
1-
#900000
1+
#912500
0+
#925000
1+
#937500
0+
#950000
1+
#962500
0+
#975000
1+
#987500
b0 4
0+
b0 (
b0 2
00
01
1*
#1000000
b1010 &
b1010 6
1+
#1012500
0!
0+
11
#1025000
1+
#1037500
1!
b10 4
0+
b1111111100000000000000000000001 (
b1111111100000000000000000000001 2
01
#1050000
b100 &
b100 6
1+
#1062500
0!
0+
11
#1075000
1+
#1087500
1!
b110 4
0+
b1111111100000000000000000000011 (
b1111111100000000000000000000011 2
01
#1100000
b1011 &
b1011 6
1+
#1112500
0!
0+
11
#1125000
1+
#1137500
1!
b1000 4
0+
b1111111100000000000000000000100 (
b1111111100000000000000000000100 2
01
#1150000
b1 &
b1 6
1+
#1162500
0!
0+
11
#1175000
1+
#1187500
1!
b1010 4
0+
b1111111100000000000000000000101 (
b1111111100000000000000000000101 2
01
#1200000
b1110 &
b1110 6
1+
#1212500
0!
0+
11
#1225000
1+
#1237500
1!
b10010 4
0+
b1111111100000000000000000001001 (
b1111111100000000000000000001001 2
01
#1250000
b1101 &
b1101 6
1+
#1262500
0!
0+
11
#1275000
1+
#1287500
1!
b10100 4
0+
b1111111100000000000000000001010 (
b1111111100000000000000000001010 2
01
#1300000
b1010 &
b1010 6
1+
#1312500
0!
0+
11
#1325000
1+
#1337500
1!
b10110 4
0+
b1111111100000000000000000001011 (
b1111111100000000000000000001011 2
01
#1350000
b111 &
b111 6
1+
#1362500
0!
0+
0-
11
#1375000
1+
#1387500
1!
b1000100 4
0+
b1001 ,
b1001 3
b1111111100000000000000000100010 (
b1111111100000000000000000100010 2
01
#1400000
1+
#1412500
0!
0+
11
#1425000
1+
#1437500
1!
b1001000 4
0+
b1111111100000000000000000100100 (
b1111111100000000000000000100100 2
01
#1450000
1+
#1462500
0!
0+
11
#1475000
1;
b1001 "
b1001 :
1+
#1487500
1!
0+
b10 .
0*
10
1-
#1500000
1+
#1512500
0+
#1525000
1+
#1537500
0+
#1550000
1+
#1562500
0+
#1575000
1+
#1587500
b0 4
0+
b0 (
b0 2
00
01
1*
#1600000
b1001 &
b1001 6
1+
#1612500
0!
0+
11
#1625000
1+
#1637500
1!
b10 4
0+
b1111111100000000000000000000001 (
b1111111100000000000000000000001 2
01
#1650000
b10 &
b10 6
1+
#1662500
0!
0+
11
#1675000
1+
#1687500
1!
b110 4
0+
b1111111100000000000000000000011 (
b1111111100000000000000000000011 2
01
#1700000
b1010 &
b1010 6
1+
#1712500
0!
0+
11
#1725000
1+
#1737500
1!
b1000 4
0+
b1111111100000000000000000000100 (
b1111111100000000000000000000100 2
01
#1750000
b1111 &
b1111 6
1+
#1762500
0!
0+
11
#1775000
1+
#1787500
1!
b1010 4
0+
b1111111100000000000000000000101 (
b1111111100000000000000000000101 2
01
#1800000
1+
#1812500
0!
0+
11
#1825000
1+
#1837500
1!
b10010 4
0+
b1111111100000000000000000001001 (
b1111111100000000000000000001001 2
01
#1850000
b1101 &
b1101 6
1+
#1862500
0!
0+
11
#1875000
1+
#1887500
1!
b10100 4
0+
b1111111100000000000000000001010 (
b1111111100000000000000000001010 2
01
#1900000
b1010 &
b1010 6
1+
#1912500
0!
0+
11
#1925000
1+
#1937500
1!
b10110 4
0+
b1111111100000000000000000001011 (
b1111111100000000000000000001011 2
01
#1950000
b111 &
b111 6
1+
#1962500
0!
0+
0-
11
#1975000
1+
#1987500
1!
b1000100 4
0+
b1010 ,
b1010 3
b1111111100000000000000000100010 (
b1111111100000000000000000100010 2
01
#2000000
1+
#2012500
0!
0+
11
#2025000
b101 7
1+
#2037500
1!
b1001000 4
0+
b1111111100000000000000000100100 (
b1111111100000000000000000100100 2
01
#2050000
1+
#2062500
0!
0+
11
#2075000
1'
18
1+
#2087500
1!
0+
b11 .
0*
10
1-
#2100000
1+
#2112500
0+
#2125000
1+
#2137500
0+
#2150000
1+
#2162500
0+
#2175000
1+
#2187500
1%
b0 4
0+
b11101010000000000000000 (
b11101010000000000000000 2
00
01
#2200000
1+
#2212500
0+
11
#2225000
1+
#2237500
0+
#2250000
1+
#2262500
0+
#2275000
1+
#2287500
0+
#2300000
1+
#2312500
0+
10
#2325000
1+
#2337500
0+
#2350000
1+
#2362500
0+
#2375000
1+
#2387500
0+
#2400000
1+
#2412500
1$
0+
0-
00
01
#2425000
1+
#2437500
0+
11
#2450000
1+
#2462500
0+
#2475000
1+
#2487500
0+
#2500000
1+
#2512500
0+
#2525000
1+
#2537500
0%
0+
b0 (
b0 2
1-
10
