Logic/U409/U409_RAM_CONTROLLER.v
/*
----------------------------------------------------------------------------------
--This work is shared under the Attribution-NonCommercial-ShareAlike 4.0 International (CC BY-NC-SA 4.0) License
--https://creativecommons.org/licenses/by-nc-sa/4.0/legalcode
	
--You are free to:
--Share - copy and redistribute the material in any medium or format
--Adapt - remix, transform, and build upon the material

--Under the following terms:

--Attribution - You must give appropriate credit, provide a link to the license, and indicate if changes were made. 
--You may do so in any reasonable manner, but not in any way that suggests the licensor endorses you or your use.

--NonCommercial - You may not use the material for commercial purposes.

--ShareAlike - If you remix, transform, or build upon the material, you must distribute your contributions under the 
--same license as the original.

--No additional restrictions - You may not apply legal terms or technological measures that legally restrict others 
--from doing anything the license permits.
--------------------------------------------------------------------------------------------------------------------------------------------------------------------
-- Engineer: Jason Neus
-- 
-- Design Name: U409
-- Module Name: RAM_CONTROLLER
-- Project Name: AmigaPCI
-- Target Devices: iCE40-HX4K-TQ144
--
-- Description: LOGIC FOR FAST RAM CONTROLLER.
--
-- Revision History:
--     07-JAN-2023 : Initial Engineering Release
--     03-MAR-2024 : Rewrite for iCE FPGA
----------------------------------------------------------------------------------
*/

module U409_RAM_CONTROLLER
(
    input CLK7,
    input CLK40,
    input CLK80,
    input [31:2] A,
    input nTIP,
    input TT0,
    input TT1,
    input RnW,
    input nRESET,	
    input EMEN,

    output wire [12:0] EMA,
    output reg BANK0,
    output reg BANK1,
    output wire nEMRAS,
    output wire nEMCAS,
    output wire EMCLKE,
    output wire nEMWE,
    output wire nEM0CS,
    output wire nEM1CS,
    output wire RAM_TA
);

localparam [3:0] ramstate_NOP = 4'b1111;
localparam [3:0] ramstate_PRECHARGE = 4'b0010;
localparam [3:0] ramstate_BANKACTIVATE = 4'b0011;
localparam [3:0] ramstate_READ = 4'b0101;
localparam [3:0] ramstate_WRITE = 4'b0100;
localparam [3:0] ramstate_AUTOREFRESH = 4'b0001;
localparam [3:0] ramstate_MODEREGISTER = 4'b0000;
localparam REFRESH_DEFAULT = 8'h36;

reg [3:0] SDRAMCOM;

///////////////////////////
// SDRAM REFRESH COUNTER //
///////////////////////////

//WE USE THE 7MHz CLOCK TO DRIVE THE REFRESH COUNTER BECAUSE THAT 
//WILL ALWAYS BE AVAILABLE NO MATTER OUR CPU SPEED OR CONFIGURATION.
//SINCE WE ARE JUMPING BETWEEN CLOCK DOMAINS, WE NEED TO HAVE
//TWO PROCESSES TO ACCOMODATE THE JUMP.

wire REF_RESET;
reg REFRESH;
reg [REFRESH_DEFAULT:0] REFRESH_COUNTER = 8'h0;

assign REF_RESET = SDRAMCOM == ramstate_AUTOREFRESH;

always @(posedge CLK7 or posedge REF_RESET) begin
    if (REF_RESET) begin REFRESH_COUNTER <= 8'h0; end
    else begin REFRESH_COUNTER <= REFRESH_COUNTER + 1; end
end

always @(negedge CLK80 or negedge nRESET) begin
    if (!nRESET) begin REFRESH <= 0; end
    else if (REFRESH_COUNTER >= REFRESH_DEFAULT) begin
        REFRESH <= 1;
    end else begin
        REFRESH <= 0;
    end
end

//////////////////////////
// SDRAM RAM CONTROLLER //
//////////////////////////

reg [3:0]RAM_COUNTER;
reg EMCLK_OUT;
reg SDRAM_CS0;
reg SDRAM_CS1;
reg RAM_CONFIGURED;
reg REFRESH_CYCLE;
reg MEMORY_CYCLE;
reg BURST_CYCLE;
reg RnW_CYCLE;
reg TA_OUT;

assign nEM0CS = !((SDRAM_CS0 || !RAM_CONFIGURED || REFRESH_CYCLE) && !SDRAMCOM[3]);
assign nEM1CS = !((SDRAM_CS1 || !RAM_CONFIGURED || REFRESH_CYCLE) && !SDRAMCOM[3]);
assign nEMRAS = SDRAMCOM[2];
assign nEMCAS = SDRAMCOM[1];	
assign nEMWE = SDRAMCOM[0];
assign EMCLKE = EMCLK_OUT;
assign RAM_TA = TA_OUT;

assign EMA = 
    SDRAMCOM == ramstate_PRECHARGE ? 13'b0010000000000 : 
    SDRAMCOM == ramstate_MODEREGISTER ? 13'b0000000100010 : 
    SDRAMCOM == ramstate_BANKACTIVATE ? {A[26],A[22:11]} : 
    SDRAMCOM == ramstate_READ || SDRAMCOM == ramstate_WRITE ? {3'b000, A[27], A[10:2]} : 13'h0;

always @(negedge CLK80, negedge nRESET) begin
    if (!nRESET) begin
        SDRAMCOM = ramstate_NOP;
        EMCLK_OUT <= 0;
        BANK0 <= 0;
        BANK1 <= 0;
        RAM_COUNTER <= 4'h0;
        RAM_CONFIGURED <= 0;
        MEMORY_CYCLE <= 0;
        REFRESH_CYCLE <= 0;
        BURST_CYCLE <= 0;
        RnW_CYCLE <= 1;
        SDRAM_CS0 <= 0;
        SDRAM_CS1 <= 0; 
        TA_OUT <= 0;
    end else begin

        //INCREMENT COUNTER DURING A CYCLE
        if (RAM_COUNTER != 4'h0) begin RAM_COUNTER <= RAM_COUNTER + 1; end

        //CONFIGURE THE RAM AT STARTUP OR RESET
        if (!RAM_CONFIGURED) begin
            case (RAM_COUNTER)
                4'h0 : begin EMCLK_OUT <= 1; RAM_COUNTER <= 4'h1; end
                4'h1 : SDRAMCOM <= ramstate_PRECHARGE;
                4'h3 : SDRAMCOM <= ramstate_MODEREGISTER;
                4'h4, 4'h9 : SDRAMCOM <= ramstate_AUTOREFRESH;
                4'hD : begin RAM_CONFIGURED <= 1; RAM_COUNTER <= 4'h0; end
				default : SDRAMCOM <= ramstate_NOP;
            endcase
        end else if (!MEMORY_CYCLE && (REFRESH_CYCLE || REFRESH)) begin
            case (RAM_COUNTER)
                4'h0 : begin RAM_COUNTER <= 4'h1; SDRAMCOM <= ramstate_AUTOREFRESH; REFRESH_CYCLE <= 1; end
                4'h4 : begin RAM_COUNTER <= 4'h0; REFRESH_CYCLE <= 0; end
                default : SDRAMCOM <= ramstate_NOP;
            endcase
        end else if ((EMEN && !nTIP) || MEMORY_CYCLE) begin
            case (RAM_COUNTER)

                4'h0 : begin 
                    TA_OUT <= 0;
                    EMCLK_OUT <= 1;

                    if (EMEN && !nTIP & !CLK40) begin
                        BANK0 <= A[23];
                        BANK1 <= A[24];
                        SDRAM_CS0 <= ~A[25]; 
                        SDRAM_CS1 <= A[25];
                        SDRAMCOM <= ramstate_BANKACTIVATE;
                        RAM_COUNTER <= 4'h1;
                        MEMORY_CYCLE <= 1;
                        BURST_CYCLE <= TT0 && !TT1;
                        RnW_CYCLE <= RnW;
                    end else begin
                        MEMORY_CYCLE <= 0;
                        SDRAMCOM <= ramstate_NOP;
                    end
                end

                4'h1 : begin
                    SDRAMCOM <= ramstate_NOP;
                    TA_OUT <= !RnW_CYCLE;
                end

                4'h2 : begin
                    if (RnW_CYCLE) begin
                        SDRAMCOM <= ramstate_READ;
                    end else begin
                        SDRAMCOM <= ramstate_WRITE;
                        if (BURST_CYCLE) begin EMCLK_OUT <= 0; end
                    end				
                end

                4'h3 : begin
                    EMCLK_OUT <= 1;
                    if (RnW_CYCLE) begin
                        TA_OUT <= 1;
                    end else begin
                        if (!BURST_CYCLE) begin TA_OUT <= 0; end
                    end

                    if (!BURST_CYCLE) begin
                        SDRAMCOM <= ramstate_PRECHARGE;
                    end else begin
                        SDRAMCOM <= ramstate_NOP;
                    end
                end

                4'h4 : begin
                    if (!BURST_CYCLE) begin
                        SDRAMCOM <= ramstate_NOP;
                        RAM_COUNTER <= 0; //IN THE CASE OF A NON-BURST WRITE, WE ADD AN EXTRA CLOCK TO MEET MIN CYCLE TIME FOR SDRAM                      
                    end else begin
                        //TA_OUT <= 0;
                        EMCLK_OUT <= 0;
                    end
                end    

                5'h5 : begin //IF WE GET THIS FAR, WE ARE CERTAINLY IN A BURST CYCLE.
                    EMCLK_OUT <= 1;
                end

                5'h6 : begin 
                    EMCLK_OUT <= 0;
                end

                5'h7 : begin
                    EMCLK_OUT <= 1;
                end

                5'h8 : begin
                    if (!RnW_CYCLE) begin 
                        TA_OUT <= 1; 
                    end else begin
                        EMCLK_OUT <= 0;
                    end
                end

                5'h9 : begin
                    EMCLK_OUT <= 1;

                    if (!RnW_CYCLE) begin
                        SDRAMCOM <= ramstate_PRECHARGE; //END OF A BURST WRITE CYCLE
                        RAM_COUNTER <= 0;
                    end
                end

                5'hB : begin
                    TA_OUT <= 0;
                    SDRAMCOM <= ramstate_PRECHARGE; //END OF A BURST READ CYCLE
                    RAM_COUNTER <= 0;
                end

            endcase
        end

    end
end

endmodule

Logic/TestBenches/U409-TESTBENCH/RAM_CONTROLLER/U409_RAM_CONTROLLER_tb.v
// Define timescale <time unit> / <time precision>
`timescale 1 ns / 10 ps
`default_nettype none

//There are no ports in a test bench.
module ram_controller_tb();

//reg regs
reg CLK7 = 1;
reg CLK40 = 1;
reg CLK80 = 1;
reg [31:2] A = 30'b000000000000000000000000000000;
reg nTIP = 1;
reg TT0 = 1;
reg TT1 = 1;
reg RnW = 1;
reg nRESET = 0;
reg EMEN = 0;

//wire outputs
wire [12:0] EMA;
wire BANK0;
wire BANK1;
wire nEMRAS;
wire nEMCAS;
wire EMCLKE;
wire nEMWE;
wire nEM0CS;
wire nEM1CS;
wire RAM_TA;

//Simulation time : 10000 * 1ns = 10us
localparam DURATION = 50000;

//Generate Clock(s)
//7.16MHz = 139ns
//40MHz = 25ns
//80MHz = 12.5ns

always #69.5 CLK7 = ~CLK7;
always #12.5 CLK40 = ~CLK40;
always #6.25 CLK80 = ~CLK80;

//THE TEST
initial begin
	#100 nRESET = 1;
    #412.5 nTIP = 0; RnW = 0; EMEN = 1; A = 30'b000000000000000000000000000011;
    #100 nTIP = 1; RnW = 1;
    #48 nTIP = 0;
    #100 nTIP = 1;
    #48 nTIP = 0; RnW = 0; TT1 = 0; ; EMEN = 1; A = 30'b000000000000000000000000001100;
    #254 nTIP = 1; RnW = 1;
    #48 nTIP = 0;
    #254 nTIP = 1;    
end

//Test Parameters
initial begin
	$dumpfile("ram_controller_tb.vcd");
	$dumpvars(0, ram_controller_tb); //0=most verbose
	//$monitor($time,,AC_ADDRESS);
	//$monitor($time,,counter);
	
	#(DURATION)
	$display("Finished");
	$finish;	
end

//Instantiate the device under test
U409_RAM_CONTROLLER dut
(
    .CLK7 (CLK7),
    .CLK40 (CLK40),
    .CLK80 (CLK80),
    .A (A),
    .nTIP (nTIP),
    .TT0 (TT0),
    .TT1 (TT1),
    .RnW (RnW),
    .nRESET (nRESET),
    .EMEN (EMEN),

    .EMA (EMA),
    .BANK0 (BANK0),
    .BANK1 (BANK1),
    .nEMRAS (nEMRAS),
    .nEMCAS (nEMCAS),
    .EMCLKE (EMCLKE),
    .nEMWE (nEMWE),
    .nEM0CS (nEM0CS),
    .nEM1CS (nEM1CS),
    .RAM_TA (RAM_TA)
);

endmodule

Logic/TestBenches/U409-TESTBENCH/RAM_CONTROLLER/ram_controller_tb.vcd
$date
	Sun Mar  3 12:59:07 2024
$end
$version
	Icarus Verilog
$end
$timescale
	1ps
$end
$scope module ram_controller_tb $end
$var wire 1 ! nEMWE $end
$var wire 1 " nEMRAS $end
$var wire 1 # nEMCAS $end
$var wire 1 $ nEM1CS $end
$var wire 1 % nEM0CS $end
$var wire 1 & RAM_TA $end
$var wire 1 ' EMCLKE $end
$var wire 13 ( EMA [12:0] $end
$var wire 1 ) BANK1 $end
$var wire 1 * BANK0 $end
$var reg 30 + A [31:2] $end
$var reg 1 , CLK40 $end
$var reg 1 - CLK7 $end
$var reg 1 . CLK80 $end
$var reg 1 / EMEN $end
$var reg 1 0 RnW $end
$var reg 1 1 TT0 $end
$var reg 1 2 TT1 $end
$var reg 1 3 nRESET $end
$var reg 1 4 nTIP $end
$scope module dut $end
$var wire 30 5 A [31:2] $end
$var wire 1 , CLK40 $end
$var wire 1 - CLK7 $end
$var wire 1 . CLK80 $end
$var wire 1 ' EMCLKE $end
$var wire 1 / EMEN $end
$var wire 1 & RAM_TA $end
$var wire 1 0 RnW $end
$var wire 1 1 TT0 $end
$var wire 1 2 TT1 $end
$var wire 1 3 nRESET $end
$var wire 1 4 nTIP $end
$var wire 1 ! nEMWE $end
$var wire 1 " nEMRAS $end
$var wire 1 # nEMCAS $end
$var wire 1 $ nEM1CS $end
$var wire 1 % nEM0CS $end
$var wire 1 6 REF_RESET $end
$var wire 13 7 EMA [12:0] $end
$var reg 1 * BANK0 $end
$var reg 1 ) BANK1 $end
$var reg 1 8 BURST_CYCLE $end
$var reg 1 9 EMCLK_OUT $end
$var reg 1 : MEMORY_CYCLE $end
$var reg 1 ; RAM_CONFIGURED $end
$var reg 4 < RAM_COUNTER [3:0] $end
$var reg 1 = REFRESH $end
$var reg 55 > REFRESH_COUNTER [54:0] $end
$var reg 1 ? REFRESH_CYCLE $end
$var reg 1 @ RnW_CYCLE $end
$var reg 4 A SDRAMCOM [3:0] $end
$var reg 1 B SDRAM_CS0 $end
$var reg 1 C SDRAM_CS1 $end
$var reg 1 D TA_OUT $end
$upscope $end
$upscope $end
$enddefinitions $end
#0
$dumpvars
0D
0C
0B
b1111 A
1@
0?
b1 >
0=
b0 <
0;
0:
09
08
b0 7
06
b0 5
14
03
12
11
10
0/
1.
1-
1,
b0 +
0*
0)
b0 (
0'
0&
1%
1$
1#
1"
1!
$end
#6250
0.
#12500
1.
0,
#18750
0.
#25000
1.
1,
#31250
0.
#37500
1.
0,
#43750
0.
#50000
1.
1,
#56250
0.
#62500
1.
0,
#68750
0.
#69500
0-
#75000
1.
1,
#81250
0.
#87500
1.
0,
#93750
0.
#100000
1.
1,
13
#106250
b1 <
1'
19
0.
#112500
1.
0,
#118750
0%
0$
0"
0!
b10000000000 (
b10000000000 7
b10 A
b10 <
0.
#125000
1.
1,
#131250
1%
1$
1"
1!
b0 (
b0 7
b1111 A
b11 <
0.
#137500
1.
0,
#139000
b10 >
1-
#143750
0%
0$
b100010 (
b100010 7
0"
0#
0!
b0 A
b100 <
0.
#150000
1.
1,
#156250
b0 >
b0 (
b0 7
1!
16
b1 A
b101 <
0.
#162500
1.
0,
#168750
1%
1$
1"
1#
06
b1111 A
b110 <
0.
#175000
1.
1,
#181250
b111 <
0.
#187500
1.
0,
#193750
b1000 <
0.
#200000
1.
1,
#206250
b1001 <
0.
#208500
0-
#212500
1.
0,
#218750
0%
0$
0"
0#
16
b1 A
b1010 <
0.
#225000
1.
1,
#231250
1%
1$
1"
1#
06
b1111 A
b1011 <
0.
#237500
1.
0,
#243750
b1100 <
0.
#250000
1.
1,
#256250
b1101 <
0.
#262500
1.
0,
#268750
1;
b0 <
0.
#275000
1.
1,
#278000
b1 >
1-
#281250
0.
#287500
1.
0,
#293750
0.
#300000
1.
1,
#306250
0.
#312500
1.
0,
#318750
0.
#325000
1.
1,
#331250
0.
#337500
1.
0,
#343750
0.
#347500
0-
#350000
1.
1,
#356250
0.
#362500
1.
0,
#368750
0.
#375000
1.
1,
#381250
0.
#387500
1.
0,
#393750
0.
#400000
1.
1,
#406250
0.
#412500
1.
0,
#417000
b10 >
1-
#418750
0.
#425000
1.
1,
#431250
0.
#437500
1.
0,
#443750
0.
#450000
1.
1,
#456250
0.
#462500
1.
0,
#468750
0.
#475000
1.
1,
#481250
0.
#486500
0-
#487500
1.
0,
#493750
0.
#500000
1.
1,
#506250
0.
#512500
1.
0,
b11 +
b11 5
1/
00
04
#518750
0%
0"
0@
1:
b1 <
b11 A
1B
0.
#525000
1.
1,
#531250
1%
1"
1&
1D
b1111 A
b10 <
0.
#537500
1.
0,
#543750
b11 (
b11 7
0%
0#
0!
b100 A
b11 <
0.
#550000
1.
1,
#556000
b11 >
1-
#556250
0"
1#
b10000000000 (
b10000000000 7
b10 A
0&
0D
b100 <
0.
#562500
1.
0,
#568750
1%
1"
1!
b0 (
b0 7
b1111 A
b0 <
0.
#575000
1.
1,
#581250
0:
0.
#587500
1.
0,
#593750
0%
0"
1:
b1 <
b11 A
0.
#600000
1.
1,
#606250
1%
1"
1&
1D
b1111 A
b10 <
0.
#612500
1.
0,
10
14
#618750
b11 (
b11 7
0%
0#
0!
b100 A
b11 <
0.
#625000
1.
1,
#625500
0-
#631250
0"
1#
b10000000000 (
b10000000000 7
b10 A
0&
0D
b100 <
0.
#637500
1.
0,
#643750
1%
1"
1!
b0 (
b0 7
b1111 A
b0 <
0.
#650000
1.
1,
#656250
0:
0.
#660500
04
#662500
1.
0,
#668750
0%
0"
1@
1:
b1 <
b11 A
0.
#675000
1.
1,
#681250
1%
1"
b1111 A
b10 <
0.
#687500
1.
0,
#693750
b11 (
b11 7
0%
0#
b101 A
b11 <
0.
#695000
b100 >
1-
#700000
1.
1,
#706250
0"
1#
0!
b10000000000 (
b10000000000 7
b10 A
1&
1D
b100 <
0.
#712500
1.
0,
#718750
1%
1"
1!
b0 (
b0 7
b1111 A
b0 <
0.
#725000
1.
1,
#731250
0:
0&
0D
0.
#737500
1.
0,
#743750
0%
0"
1:
b1 <
b11 A
0.
#750000
1.
1,
#756250
1%
1"
b1111 A
b10 <
0.
#760500
14
#762500
1.
0,
#764500
0-
#768750
b11 (
b11 7
0%
0#
b101 A
b11 <
0.
#775000
1.
1,
#781250
0"
1#
0!
b10000000000 (
b10000000000 7
b10 A
1&
1D
b100 <
0.
#787500
1.
0,
#793750
1%
1"
1!
b0 (
b0 7
b1111 A
b0 <
0.
#800000
1.
1,
#806250
0:
0&
0D
0.
#808500
b1100 +
b1100 5
02
00
04
#812500
1.
0,
#818750
0%
0"
0@
18
1:
b1 <
b11 A
0.
#825000
1.
1,
#831250
1%
1"
1&
1D
b1111 A
b10 <
0.
#834000
b101 >
1-
#837500
1.
0,
#843750
b1100 (
b1100 7
0%
0#
0!
0'
09
b100 A
b11 <
0.
#850000
1.
1,
#856250
b0 (
b0 7
1%
1#
1!
b1111 A
1'
19
b100 <
0.
#862500
1.
0,
#868750
0'
09
b101 <
0.
#875000
1.
1,
#881250
1'
19
b110 <
0.
#887500
1.
0,
#893750
0'
09
b111 <
0.
#900000
1.
1,
#903500
0-
#906250
1'
19
b1000 <
0.
#912500
1.
0,
#918750
b1001 <
0.
#925000
1.
1,
#931250
0%
0"
0!
b10000000000 (
b10000000000 7
b10 A
b0 <
0.
#937500
1.
0,
#943750
1!
b0 (
b0 7
b1 <
b11 A
0&
0D
0.
#950000
1.
1,
#956250
1%
1"
1&
1D
b1111 A
b10 <
0.
#962500
1.
0,
#968750
b1100 (
b1100 7
0%
0#
0!
0'
09
b100 A
b11 <
0.
#973000
b110 >
1-
#975000
1.
1,
#981250
b0 (
b0 7
1%
1#
1!
b1111 A
1'
19
b100 <
0.
#987500
1.
0,
#993750
0'
09
b101 <
0.
#1000000
1.
1,
#1006250
1'
19
b110 <
0.
#1012500
1.
0,
#1018750
0'
09
b111 <
0.
#1025000
1.
1,
#1031250
1'
19
b1000 <
0.
#1037500
1.
0,
#1042500
0-
#1043750
b1001 <
0.
#1050000
1.
1,
#1056250
0%
0"
0!
b10000000000 (
b10000000000 7
b10 A
b0 <
0.
#1062500
1.
0,
10
14
#1068750
1%
1"
1!
b0 (
b0 7
b1111 A
0:
0&
0D
0.
#1075000
1.
1,
#1081250
0.
#1087500
1.
0,
#1093750
0.
#1100000
1.
1,
#1106250
0.
#1110500
04
#1112000
b111 >
1-
#1112500
1.
0,
#1118750
0%
0"
1@
1:
b1 <
b11 A
0.
#1125000
1.
1,
#1131250
1%
1"
b1111 A
b10 <
0.
#1137500
1.
0,
#1143750
b1100 (
b1100 7
0%
0#
b101 A
b11 <
0.
#1150000
1.
1,
#1156250
b0 (
b0 7
1%
1#
b1111 A
1&
1D
b100 <
0.
#1162500
1.
0,
#1168750
0'
09
b101 <
0.
#1175000
1.
1,
#1181250
1'
19
b110 <
0.
#1181500
0-
#1187500
1.
0,
#1193750
0'
09
b111 <
0.
#1200000
1.
1,
#1206250
1'
19
b1000 <
0.
#1212500
1.
0,
#1218750
0'
09
b1001 <
0.
#1225000
1.
1,
#1231250
1'
19
b1010 <
0.
#1237500
1.
0,
#1243750
b1011 <
0.
#1250000
1.
1,
#1251000
b1000 >
1-
#1256250
0%
0"
0!
b10000000000 (
b10000000000 7
b10 A
0&
0D
b0 <
0.
#1262500
1.
0,
#1268750
1!
b0 (
b0 7
b1 <
b11 A
0.
#1275000
1.
1,
#1281250
1%
1"
b1111 A
b10 <
0.
#1287500
1.
0,
#1293750
b1100 (
b1100 7
0%
0#
b101 A
b11 <
0.
#1300000
1.
1,
#1306250
b0 (
b0 7
1%
1#
b1111 A
1&
1D
b100 <
0.
#1312500
1.
0,
#1318750
0'
09
b101 <
0.
#1320500
0-
#1325000
1.
1,
#1331250
1'
19
b110 <
0.
#1337500
1.
0,
#1343750
0'
09
b111 <
0.
#1350000
1.
1,
#1356250
1'
19
b1000 <
0.
#1362500
1.
0,
#1364500
14
#1368750
0'
09
b1001 <
0.
#1375000
1.
1,
#1381250
1'
19
b1010 <
0.
#1387500
1.
0,
#1390000
b1001 >
1-
#1393750
b1011 <
0.
#1400000
1.
1,
#1406250
0%
0"
0!
b10000000000 (
b10000000000 7
b10 A
0&
0D
b0 <
0.
#1412500
1.
0,
#1418750
1%
1"
1!
b0 (
b0 7
b1111 A
0:
0.
#1425000
1.
1,
#1431250
0.
#1437500
1.
0,
#1443750
0.
#1450000
1.
1,
#1456250
0.
#1459500
0-
#1462500
1.
0,
#1468750
0.
#1475000
1.
1,
#1481250
0.
#1487500
1.
0,
#1493750
0.
#1500000
1.
1,
#1506250
0.
#1512500
1.
0,
#1518750
0.
#1525000
1.
1,
#1529000
b1010 >
1-
#1531250
0.
#1537500
1.
0,
#1543750
0.
#1550000
1.
1,
#1556250
0.
#1562500
1.
0,
#1568750
0.
#1575000
1.
1,
#1581250
0.
#1587500
1.
0,
#1593750
0.
#1598500
0-
#1600000
1.
1,
#1606250
0.
#1612500
1.
0,
#1618750
0.
#1625000
1.
1,
#1631250
0.
#1637500
1.
0,
#1643750
0.
#1650000
1.
1,
#1656250
0.
#1662500
1.
0,
#1668000
b1011 >
1-
#1668750
0.
#1675000
1.
1,
#1681250
0.
#1687500
1.
0,
#1693750
0.
#1700000
1.
1,
#1706250
0.
#1712500
1.
0,
#1718750
0.
#1725000
1.
1,
#1731250
0.
#1737500
1.
0,
0-
#1743750
0.
#1750000
1.
1,
#1756250
0.
#1762500
1.
0,
#1768750
0.
#1775000
1.
1,
#1781250
0.
#1787500
1.
0,
#1793750
0.
#1800000
1.
1,
#1806250
0.
#1807000
b1100 >
1-
#1812500
1.
0,
#1818750
0.
#1825000
1.
1,
#1831250
0.
#1837500
1.
0,
#1843750
0.
#1850000
1.
1,
#1856250
0.
#1862500
1.
0,
#1868750
0.
#1875000
1.
1,
#1876500
0-
#1881250
0.
#1887500
1.
0,
#1893750
0.
#1900000
1.
1,
#1906250
0.
#1912500
1.
0,
#1918750
0.
#1925000
1.
1,
#1931250
0.
#1937500
1.
0,
#1943750
0.
#1946000
b1101 >
1-
#1950000
1.
1,
#1956250
0.
#1962500
1.
0,
#1968750
0.
#1975000
1.
1,
#1981250
0.
#1987500
1.
0,
#1993750
0.
#2000000
1.
1,
#2006250
0.
#2012500
1.
0,
#2015500
0-
#2018750
0.
#2025000
1.
1,
#2031250
0.
#2037500
1.
0,
#2043750
0.
#2050000
1.
1,
#2056250
0.
#2062500
1.
0,
#2068750
0.
#2075000
1.
1,
#2081250
0.
#2085000
b1110 >
1-
#2087500
1.
0,
#2093750
0.
#2100000
1.
1,
#2106250
0.
#2112500
1.
0,
#2118750
0.
#2125000
1.
1,
#2131250
0.
#2137500
1.
0,
#2143750
0.
#2150000
1.
1,
#2154500
0-
#2156250
0.
#2162500
1.
0,
#2168750
0.
#2175000
1.
1,
#2181250
0.
#2187500
1.
0,
#2193750
0.
#2200000
1.
1,
#2206250
0.
#2212500
1.
0,
#2218750
0.
#2224000
b1111 >
1-
#2225000
1.
1,
#2231250
0.
#2237500
1.
0,
#2243750
0.
#2250000
1.
1,
#2256250
0.
#2262500
1.
0,
#2268750
0.
#2275000
1.
1,
#2281250
0.
#2287500
1.
0,
#2293500
0-
#2293750
0.
#2300000
1.
1,
#2306250
0.
#2312500
1.
0,
#2318750
0.
#2325000
1.
1,
#2331250
0.
#2337500
1.
0,
#2343750
0.
#2350000
1.
1,
#2356250
0.
#2362500
1.
0,
#2363000
b10000 >
1-
#2368750
0.
#2375000
1.
1,
#2381250
0.
#2387500
1.
0,
#2393750
0.
#2400000
1.
1,
#2406250
0.
#2412500
1.
0,
#2418750
0.
#2425000
1.
1,
#2431250
0.
#2432500
0-
#2437500
1.
0,
#2443750
0.
#2450000
1.
1,
#2456250
0.
#2462500
1.
0,
#2468750
0.
#2475000
1.
1,
#2481250
0.
#2487500
1.
0,
#2493750
0.
#2500000
1.
1,
#2502000
b10001 >
1-
#2506250
0.
#2512500
1.
0,
#2518750
0.
#2525000
1.
1,
#2531250
0.
#2537500
1.
0,
#2543750
0.
#2550000
1.
1,
#2556250
0.
#2562500
1.
0,
#2568750
0.
#2571500
0-
#2575000
1.
1,
#2581250
0.
#2587500
1.
0,
#2593750
0.
#2600000
1.
1,
#2606250
0.
#2612500
1.
0,
#2618750
0.
#2625000
1.
1,
#2631250
0.
#2637500
1.
0,
#2641000
b10010 >
1-
#2643750
0.
#2650000
1.
1,
#2656250
0.
#2662500
1.
0,
#2668750
0.
#2675000
1.
1,
#2681250
0.
#2687500
1.
0,
#2693750
0.
#2700000
1.
1,
#2706250
0.
#2710500
0-
#2712500
1.
0,
#2718750
0.
#2725000
1.
1,
#2731250
0.
#2737500
1.
0,
#2743750
0.
#2750000
1.
1,
#2756250
0.
#2762500
1.
0,
#2768750
0.
#2775000
1.
1,
#2780000
b10011 >
1-
#2781250
0.
#2787500
1.
0,
#2793750
0.
#2800000
1.
1,
#2806250
0.
#2812500
1.
0,
#2818750
0.
#2825000
1.
1,
#2831250
0.
#2837500
1.
0,
#2843750
0.
#2849500
0-
#2850000
1.
1,
#2856250
0.
#2862500
1.
0,
#2868750
0.
#2875000
1.
1,
#2881250
0.
#2887500
1.
0,
#2893750
0.
#2900000
1.
1,
#2906250
0.
#2912500
1.
0,
#2918750
0.
#2919000
b10100 >
1-
#2925000
1.
1,
#2931250
0.
#2937500
1.
0,
#2943750
0.
#2950000
1.
1,
#2956250
0.
#2962500
1.
0,
#2968750
0.
#2975000
1.
1,
#2981250
0.
#2987500
1.
0,
#2988500
0-
#2993750
0.
#3000000
1.
1,
#3006250
0.
#3012500
1.
0,
#3018750
0.
#3025000
1.
1,
#3031250
0.
#3037500
1.
0,
#3043750
0.
#3050000
1.
1,
#3056250
0.
#3058000
b10101 >
1-
#3062500
1.
0,
#3068750
0.
#3075000
1.
1,
#3081250
0.
#3087500
1.
0,
#3093750
0.
#3100000
1.
1,
#3106250
0.
#3112500
1.
0,
#3118750
0.
#3125000
1.
1,
#3127500
0-
#3131250
0.
#3137500
1.
0,
#3143750
0.
#3150000
1.
1,
#3156250
0.
#3162500
1.
0,
#3168750
0.
#3175000
1.
1,
#3181250
0.
#3187500
1.
0,
#3193750
0.
#3197000
b10110 >
1-
#3200000
1.
1,
#3206250
0.
#3212500
1.
0,
#3218750
0.
#3225000
1.
1,
#3231250
0.
#3237500
1.
0,
#3243750
0.
#3250000
1.
1,
#3256250
0.
#3262500
1.
0,
#3266500
0-
#3268750
0.
#3275000
1.
1,
#3281250
0.
#3287500
1.
0,
#3293750
0.
#3300000
1.
1,
#3306250
0.
#3312500
1.
0,
#3318750
0.
#3325000
1.
1,
#3331250
0.
#3336000
b10111 >
1-
#3337500
1.
0,
#3343750
0.
#3350000
1.
1,
#3356250
0.
#3362500
1.
0,
#3368750
0.
#3375000
1.
1,
#3381250
0.
#3387500
1.
0,
#3393750
0.
#3400000
1.
1,
#3405500
0-
#3406250
0.
#3412500
1.
0,
#3418750
0.
#3425000
1.
1,
#3431250
0.
#3437500
1.
0,
#3443750
0.
#3450000
1.
1,
#3456250
0.
#3462500
1.
0,
#3468750
0.
#3475000
b11000 >
1.
1,
1-
#3481250
0.
#3487500
1.
0,
#3493750
0.
#3500000
1.
1,
#3506250
0.
#3512500
1.
0,
#3518750
0.
#3525000
1.
1,
#3531250
0.
#3537500
1.
0,
#3543750
0.
#3544500
0-
#3550000
1.
1,
#3556250
0.
#3562500
1.
0,
#3568750
0.
#3575000
1.
1,
#3581250
0.
#3587500
1.
0,
#3593750
0.
#3600000
1.
1,
#3606250
0.
#3612500
1.
0,
#3614000
b11001 >
1-
#3618750
0.
#3625000
1.
1,
#3631250
0.
#3637500
1.
0,
#3643750
0.
#3650000
1.
1,
#3656250
0.
#3662500
1.
0,
#3668750
0.
#3675000
1.
1,
#3681250
0.
#3683500
0-
#3687500
1.
0,
#3693750
0.
#3700000
1.
1,
#3706250
0.
#3712500
1.
0,
#3718750
0.
#3725000
1.
1,
#3731250
0.
#3737500
1.
0,
#3743750
0.
#3750000
1.
1,
#3753000
b11010 >
1-
#3756250
0.
#3762500
1.
0,
#3768750
0.
#3775000
1.
1,
#3781250
0.
#3787500
1.
0,
#3793750
0.
#3800000
1.
1,
#3806250
0.
#3812500
1.
0,
#3818750
0.
#3822500
0-
#3825000
1.
1,
#3831250
0.
#3837500
1.
0,
#3843750
0.
#3850000
1.
1,
#3856250
0.
#3862500
1.
0,
#3868750
0.
#3875000
1.
1,
#3881250
0.
#3887500
1.
0,
#3892000
b11011 >
1-
#3893750
0.
#3900000
1.
1,
#3906250
0.
#3912500
1.
0,
#3918750
0.
#3925000
1.
1,
#3931250
0.
#3937500
1.
0,
#3943750
0.
#3950000
1.
1,
#3956250
0.
#3961500
0-
#3962500
1.
0,
#3968750
0.
#3975000
1.
1,
#3981250
0.
#3987500
1.
0,
#3993750
0.
#4000000
1.
1,
#4006250
0.
#4012500
1.
0,
#4018750
0.
#4025000
1.
1,
#4031000
b11100 >
1-
#4031250
0.
#4037500
1.
0,
