Logic/TestBenches/U409-TESTBENCH/U409_RAM_CONTROLLER.v
/*
----------------------------------------------------------------------------------
--This work is shared under the Attribution-NonCommercial-ShareAlike 4.0 International (CC BY-NC-SA 4.0) License
--https://creativecommons.org/licenses/by-nc-sa/4.0/legalcode
	
--You are free to:
--Share - copy and redistribute the material in any medium or format
--Adapt - remix, transform, and build upon the material

--Under the following terms:

--Attribution - You must give appropriate credit, provide a link to the license, and indicate if changes were made. 
--You may do so in any reasonable manner, but not in any way that suggests the licensor endorses you or your use.

--NonCommercial - You may not use the material for commercial purposes.

--ShareAlike - If you remix, transform, or build upon the material, you must distribute your contributions under the 
--same license as the original.

--No additional restrictions - You may not apply legal terms or technological measures that legally restrict others 
--from doing anything the license permits.
--------------------------------------------------------------------------------------------------------------------------------------------------------------------
-- Engineer: Jason Neus
-- 
-- Design Name: U409
-- Module Name: RAM_CONTROLLER
-- Project Name: AmigaPCI
-- Target Devices: XC95144XL 144 PIN
--
-- Description: LOGIC FOR FAST RAM CONTROLLER.
--
-- Revision History:
--     07-JAN-2023 : Initial Engineering Release
----------------------------------------------------------------------------------
*/

module U409_RAM_CONTROLLER
(
    input CLK7,
    input CLK40,
    input CLK80,
    input [31:2] A,
    input nTIP,
    input TT0,
    input TT1,
    input RnW,
    input nRESET,	
    //input nEMEN,

    //MEMORY_CYCLE : INOUT STD_LOGIC,
    output reg [12:0] EMA,
    output reg BANK0,
    output reg BANK1,
    output reg nEMRAS,
    output reg nEMCAS,
    output reg EMCLKE,
    output reg nEMWE,
    output reg nEM0CS,
    output reg nEM1CS,
    output reg RAM_TA
);

localparam [3:0] ramstate_NOP = 4'b1111;
localparam [3:0] ramstate_PRECHARGE = 4'b0010;
localparam [3:0] ramstate_BANKACTIVATE = 4'b0011;
localparam [3:0] ramstate_READ = 4'b0101;
localparam [3:0] ramstate_WRITE = 4'b0100;
localparam [3:0] ramstate_AUTOREFRESH = 4'b0001;
localparam [3:0] ramstate_MODEREGISTER = 4'b0000;
localparam REFRESH_DEFAULT = 8'h36;

reg [3:0] SDRAMCOM;

///////////////////////////
// SDRAM REFRESH COUNTER //
///////////////////////////

//WE USE THE 7MHz CLOCK TO DRIVE THE REFRESH COUNTER BECAUSE THAT 
//WILL ALWAYS BE AVAILABLE NO MATTER OUR CPU SPEED OR CONFIGURATION.
//SINCE WE ARE JUMPING BETWEEN CLOCK DOMAINS, WE NEED TO HAVE
//TWO PROCESSES TO ACCOMODATE THE JUMP.

wire REF_RESET;
reg REFRESH;
reg [REFRESH_DEFAULT:0] REFRESH_COUNTER = 1'h0;

assign REF_RESET = SDRAMCOM == ramstate_AUTOREFRESH;

always @(posedge CLK7 or posedge REF_RESET) begin
    if (REF_RESET) begin REFRESH_COUNTER <= 1'h0; end
    else begin REFRESH_COUNTER <= REFRESH_COUNTER + 1; end
end

always @(negedge CLK80 or negedge nRESET) begin
    if (!nRESET) begin REFRESH <= 0; end
    else if (REFRESH_COUNTER == REFRESH_DEFAULT || REFRESH) begin
        REFRESH <= 1;
    end else begin
        REFRESH <= 0;
    end
end


always @(negedge CLK80, negedge nRESET) begin
    if (!nRESET) begin
        SDRAMCOM = ramstate_NOP;
    end else begin

    end
end

endmodule

Logic/TestBenches/U409-TESTBENCH/U409_RAM_CONTROLLER_tb.v
// Define timescale <time unit> / <time precision>
`timescale 1 ns / 10 ps
`default_nettype none

//There are no ports in a test bench.
module ram_controller_tb();

//reg regs
reg CLK7 = 1;
reg CLK40 = 1;
reg CLK80 = 1;
reg [31:2] A = 30'b000000000000000000000000000000;
reg nTIP = 1;
reg TT0 = 1;
reg TT1 = 1;
reg RnW = 1;
reg nRESET = 0;	

//wire outputs
wire [12:0] EMA;
wire BANK0;
wire BANK1;
wire nEMRAS;
wire nEMCAS;
wire EMCLKE;
wire nEMWE;
wire nEM0CS;
wire nEM1CS;
wire RAM_TA;

//Simulation time : 10000 * 1ns = 10us
localparam DURATION = 10000;

//Generate Clock(s)
//7.16MHz = 139ns
//40MHz = 25ns
//80MHz = 12.5ns

always #69.5 CLK7 = ~CLK7;
always #12.5 CLK40 = ~CLK40;
always #6.25 CLK80 = ~CLK80;

//THE TEST
initial begin
	#100 nRESET = 1;    
    
end

//Test Parameters
initial begin
	$dumpfile("ram_controller_tb.vcd");
	$dumpvars(0, ram_controller_tb); //0=most verbose
	//$monitor($time,,AC_ADDRESS);
	//$monitor($time,,counter);
	
	#(DURATION)
	$display("Finished");
	$finish;	
end

//Instantiate the device under test
U409_RAM_CONTROLLER dut
(
    .CLK7 (CLK7),
    .CLK40 (CLK40),
    .CLK80 (CLK80),
    .A (A),
    .nTIP (nTIP),
    .TT0 (TT0),
    .TT1 (TT1),
    .RnW (RnW),
    .nRESET (nRESET),

    .EMA (EMA),
    .BANK0 (BANK0),
    .BANK1 (BANK1),
    .nEMRAS (nEMRAS),
    .nEMCAS (nEMCAS),
    .EMCLKE (EMCLKE),
    .nEMWE (nEMWE),
    .nEM0CS (nEM0CS),
    .nEM1CS (nEM1CS),
    .RAM_TA (RAM_TA)
);

endmodule

Logic/TestBenches/U409-TESTBENCH/ram_controller_tb.vcd
$date
	Sat Mar  2 19:42:01 2024
$end
$version
	Icarus Verilog
$end
$timescale
	1ps
$end
$scope module ram_controller_tb $end
$var wire 1 ! nEMWE $end
$var wire 1 " nEMRAS $end
$var wire 1 # nEMCAS $end
$var wire 1 $ nEM1CS $end
$var wire 1 % nEM0CS $end
$var wire 1 & RAM_TA $end
$var wire 1 ' EMCLKE $end
$var wire 13 ( EMA [12:0] $end
$var wire 1 ) BANK1 $end
$var wire 1 * BANK0 $end
$var reg 30 + A [31:2] $end
$var reg 1 , CLK40 $end
$var reg 1 - CLK7 $end
$var reg 1 . CLK80 $end
$var reg 1 / RnW $end
$var reg 1 0 TT0 $end
$var reg 1 1 TT1 $end
$var reg 1 2 nRESET $end
$var reg 1 3 nTIP $end
$scope module dut $end
$var wire 30 4 A [31:2] $end
$var wire 1 , CLK40 $end
$var wire 1 - CLK7 $end
$var wire 1 . CLK80 $end
$var wire 1 / RnW $end
$var wire 1 0 TT0 $end
$var wire 1 1 TT1 $end
$var wire 1 2 nRESET $end
$var wire 1 3 nTIP $end
$var wire 1 5 REF_RESET $end
$var reg 1 * BANK0 $end
$var reg 1 ) BANK1 $end
$var reg 13 6 EMA [12:0] $end
$var reg 1 ' EMCLKE $end
$var reg 1 & RAM_TA $end
$var reg 1 7 REFRESH $end
$var reg 55 8 REFRESH_COUNTER [54:0] $end
$var reg 4 9 SDRAMCOM [3:0] $end
$var reg 1 % nEM0CS $end
$var reg 1 $ nEM1CS $end
$var reg 1 # nEMCAS $end
$var reg 1 " nEMRAS $end
$var reg 1 ! nEMWE $end
$upscope $end
$upscope $end
$enddefinitions $end
#0
$dumpvars
b1111 9
b1 8
07
bx 6
05
b0 4
13
02
11
10
1/
1.
1-
1,
b0 +
x*
x)
bx (
x'
x&
x%
x$
x#
x"
x!
$end
#6250
0.
#12500
1.
0,
#18750
0.
#25000
1.
1,
#31250
0.
#37500
1.
0,
#43750
0.
#50000
1.
1,
#56250
0.
#62500
1.
0,
#68750
0.
#69500
0-
#75000
1.
1,
#81250
0.
#87500
1.
0,
#93750
0.
#100000
1.
1,
12
#106250
0.
#112500
1.
0,
#118750
0.
#125000
1.
1,
#131250
0.
#137500
1.
0,
#139000
b10 8
1-
#143750
0.
#150000
1.
1,
#156250
0.
#162500
1.
0,
#168750
0.
#175000
1.
1,
#181250
0.
#187500
1.
0,
#193750
0.
#200000
1.
1,
#206250
0.
#208500
0-
#212500
1.
0,
#218750
0.
#225000
1.
1,
#231250
0.
#237500
1.
0,
#243750
0.
#250000
1.
1,
#256250
0.
#262500
1.
0,
#268750
0.
#275000
1.
1,
#278000
b11 8
1-
#281250
0.
#287500
1.
0,
#293750
0.
#300000
1.
1,
#306250
0.
#312500
1.
0,
#318750
0.
#325000
1.
1,
#331250
0.
#337500
1.
0,
#343750
0.
#347500
0-
#350000
1.
1,
#356250
0.
#362500
1.
0,
#368750
0.
#375000
1.
1,
#381250
0.
#387500
1.
0,
#393750
0.
#400000
1.
1,
#406250
0.
#412500
1.
0,
#417000
b100 8
1-
#418750
0.
#425000
1.
1,
#431250
0.
#437500
1.
0,
#443750
0.
#450000
1.
1,
#456250
0.
#462500
1.
0,
#468750
0.
#475000
1.
1,
#481250
0.
#486500
0-
#487500
1.
0,
#493750
0.
#500000
1.
1,
#506250
0.
#512500
1.
0,
#518750
0.
#525000
1.
1,
#531250
0.
#537500
1.
0,
#543750
0.
#550000
1.
1,
#556000
b101 8
1-
#556250
0.
#562500
1.
0,
#568750
0.
#575000
1.
1,
#581250
0.
#587500
1.
0,
#593750
0.
#600000
1.
1,
#606250
0.
#612500
1.
0,
#618750
0.
#625000
1.
1,
#625500
0-
#631250
0.
#637500
1.
0,
#643750
0.
#650000
1.
1,
#656250
0.
#662500
1.
0,
#668750
0.
#675000
1.
1,
#681250
0.
#687500
1.
0,
#693750
0.
#695000
b110 8
1-
#700000
1.
1,
#706250
0.
#712500
1.
0,
#718750
0.
#725000
1.
1,
#731250
0.
#737500
1.
0,
#743750
0.
#750000
1.
1,
#756250
0.
#762500
1.
0,
#764500
0-
#768750
0.
#775000
1.
1,
#781250
0.
#787500
1.
0,
#793750
0.
#800000
1.
1,
#806250
0.
#812500
1.
0,
#818750
0.
#825000
1.
1,
#831250
0.
#834000
b111 8
1-
#837500
1.
0,
#843750
0.
#850000
1.
1,
#856250
0.
#862500
1.
0,
#868750
0.
#875000
1.
1,
#881250
0.
#887500
1.
0,
#893750
0.
#900000
1.
1,
#903500
0-
#906250
0.
#912500
1.
0,
#918750
0.
#925000
1.
1,
#931250
0.
#937500
1.
0,
#943750
0.
#950000
1.
1,
#956250
0.
#962500
1.
0,
#968750
0.
#973000
b1000 8
1-
#975000
1.
1,
#981250
0.
#987500
1.
0,
#993750
0.
#1000000
1.
1,
#1006250
0.
#1012500
1.
0,
#1018750
0.
#1025000
1.
1,
#1031250
0.
#1037500
1.
0,
#1042500
0-
#1043750
0.
#1050000
1.
1,
#1056250
0.
#1062500
1.
0,
#1068750
0.
#1075000
1.
1,
#1081250
0.
#1087500
1.
0,
#1093750
0.
#1100000
1.
1,
#1106250
0.
#1112000
b1001 8
1-
#1112500
1.
0,
#1118750
0.
#1125000
1.
1,
#1131250
0.
#1137500
1.
0,
#1143750
0.
#1150000
1.
1,
#1156250
0.
#1162500
1.
0,
#1168750
0.
#1175000
1.
1,
#1181250
0.
#1181500
0-
#1187500
1.
0,
#1193750
0.
#1200000
1.
1,
#1206250
0.
#1212500
1.
0,
#1218750
0.
#1225000
1.
1,
#1231250
0.
#1237500
1.
0,
#1243750
0.
#1250000
1.
1,
#1251000
b1010 8
1-
#1256250
0.
#1262500
1.
0,
#1268750
0.
#1275000
1.
1,
#1281250
0.
#1287500
1.
0,
#1293750
0.
#1300000
1.
1,
#1306250
0.
#1312500
1.
0,
#1318750
0.
#1320500
0-
#1325000
1.
1,
#1331250
0.
#1337500
1.
0,
#1343750
0.
#1350000
1.
1,
#1356250
0.
#1362500
1.
0,
#1368750
0.
#1375000
1.
1,
#1381250
0.
#1387500
1.
0,
#1390000
b1011 8
1-
#1393750
0.
#1400000
1.
1,
#1406250
0.
#1412500
1.
0,
#1418750
0.
#1425000
1.
1,
#1431250
0.
#1437500
1.
0,
#1443750
0.
#1450000
1.
1,
#1456250
0.
#1459500
0-
#1462500
1.
0,
#1468750
0.
#1475000
1.
1,
#1481250
0.
#1487500
1.
0,
#1493750
0.
#1500000
1.
1,
#1506250
0.
#1512500
1.
0,
#1518750
0.
#1525000
1.
1,
#1529000
b1100 8
1-
#1531250
0.
#1537500
1.
0,
#1543750
0.
#1550000
1.
1,
#1556250
0.
#1562500
1.
0,
#1568750
0.
#1575000
1.
1,
#1581250
0.
#1587500
1.
0,
#1593750
0.
#1598500
0-
#1600000
1.
1,
#1606250
0.
#1612500
1.
0,
#1618750
0.
#1625000
1.
1,
#1631250
0.
#1637500
1.
0,
#1643750
0.
#1650000
1.
1,
#1656250
0.
#1662500
1.
0,
#1668000
b1101 8
1-
#1668750
0.
#1675000
1.
1,
#1681250
0.
#1687500
1.
0,
#1693750
0.
#1700000
1.
1,
#1706250
0.
#1712500
1.
0,
#1718750
0.
#1725000
1.
1,
#1731250
0.
#1737500
1.
0,
0-
#1743750
0.
#1750000
1.
1,
#1756250
0.
#1762500
1.
0,
#1768750
0.
#1775000
1.
1,
#1781250
0.
#1787500
1.
0,
#1793750
0.
#1800000
1.
1,
#1806250
0.
#1807000
b1110 8
1-
#1812500
1.
0,
#1818750
0.
#1825000
1.
1,
#1831250
0.
#1837500
1.
0,
#1843750
0.
#1850000
1.
1,
#1856250
0.
#1862500
1.
0,
#1868750
0.
#1875000
1.
1,
#1876500
0-
#1881250
0.
#1887500
1.
0,
#1893750
0.
#1900000
1.
1,
#1906250
0.
#1912500
1.
0,
#1918750
0.
#1925000
1.
1,
#1931250
0.
#1937500
1.
0,
#1943750
0.
#1946000
b1111 8
1-
#1950000
1.
1,
#1956250
0.
#1962500
1.
0,
#1968750
0.
#1975000
1.
1,
#1981250
0.
#1987500
1.
0,
#1993750
0.
#2000000
1.
1,
#2006250
0.
#2012500
1.
0,
#2015500
0-
#2018750
0.
#2025000
1.
1,
#2031250
0.
#2037500
1.
0,
#2043750
0.
#2050000
1.
1,
#2056250
0.
#2062500
1.
0,
#2068750
0.
#2075000
1.
1,
#2081250
0.
#2085000
b10000 8
1-
#2087500
1.
0,
#2093750
0.
#2100000
1.
1,
#2106250
0.
#2112500
1.
0,
#2118750
0.
#2125000
1.
1,
#2131250
0.
#2137500
1.
0,
#2143750
0.
#2150000
1.
1,
#2154500
0-
#2156250
0.
#2162500
1.
0,
#2168750
0.
#2175000
1.
1,
#2181250
0.
#2187500
1.
0,
#2193750
0.
#2200000
1.
1,
#2206250
0.
#2212500
1.
0,
#2218750
0.
#2224000
b10001 8
1-
#2225000
1.
1,
#2231250
0.
#2237500
1.
0,
#2243750
0.
#2250000
1.
1,
#2256250
0.
#2262500
1.
0,
#2268750
0.
#2275000
1.
1,
#2281250
0.
#2287500
1.
0,
#2293500
0-
#2293750
0.
#2300000
1.
1,
#2306250
0.
#2312500
1.
0,
#2318750
0.
#2325000
1.
1,
#2331250
0.
#2337500
1.
0,
#2343750
0.
#2350000
1.
1,
#2356250
0.
#2362500
1.
0,
#2363000
b10010 8
1-
#2368750
0.
#2375000
1.
1,
#2381250
0.
#2387500
1.
0,
#2393750
0.
#2400000
1.
1,
#2406250
0.
#2412500
1.
0,
#2418750
0.
#2425000
1.
1,
#2431250
0.
#2432500
0-
#2437500
1.
0,
#2443750
0.
#2450000
1.
1,
#2456250
0.
#2462500
1.
0,
#2468750
0.
#2475000
1.
1,
#2481250
0.
#2487500
1.
0,
#2493750
0.
#2500000
1.
1,
#2502000
b10011 8
1-
#2506250
0.
#2512500
1.
0,
#2518750
0.
#2525000
1.
1,
#2531250
0.
#2537500
1.
0,
#2543750
0.
#2550000
1.
1,
#2556250
0.
#2562500
1.
0,
#2568750
0.
#2571500
0-
#2575000
1.
1,
#2581250
0.
#2587500
1.
0,
#2593750
0.
#2600000
1.
1,
#2606250
0.
#2612500
1.
0,
#2618750
0.
#2625000
1.
1,
#2631250
0.
#2637500
1.
0,
#2641000
b10100 8
1-
#2643750
0.
#2650000
1.
1,
#2656250
0.
#2662500
1.
0,
#2668750
0.
#2675000
1.
1,
#2681250
0.
#2687500
1.
0,
#2693750
0.
#2700000
1.
1,
#2706250
0.
#2710500
0-
#2712500
1.
0,
#2718750
0.
#2725000
1.
1,
#2731250
0.
#2737500
1.
0,
#2743750
0.
#2750000
1.
1,
#2756250
0.
#2762500
1.
0,
#2768750
0.
#2775000
1.
1,
#2780000
b10101 8
1-
#2781250
0.
#2787500
1.
0,
#2793750
0.
#2800000
1.
1,
#2806250
0.
#2812500
1.
0,
#2818750
0.
#2825000
1.
1,
#2831250
0.
#2837500
1.
0,
#2843750
0.
#2849500
0-
#2850000
1.
1,
#2856250
0.
#2862500
1.
0,
#2868750
0.
#2875000
1.
1,
#2881250
0.
#2887500
1.
0,
#2893750
0.
#2900000
1.
1,
#2906250
0.
#2912500
1.
0,
#2918750
0.
#2919000
b10110 8
1-
#2925000
1.
1,
#2931250
0.
#2937500
1.
0,
#2943750
0.
#2950000
1.
1,
#2956250
0.
#2962500
1.
0,
#2968750
0.
#2975000
1.
1,
#2981250
0.
#2987500
1.
0,
#2988500
0-
#2993750
0.
#3000000
1.
1,
#3006250
0.
#3012500
1.
0,
#3018750
0.
#3025000
1.
1,
#3031250
0.
#3037500
1.
0,
#3043750
0.
#3050000
1.
1,
#3056250
0.
#3058000
b10111 8
1-
#3062500
1.
0,
#3068750
0.
#3075000
1.
1,
#3081250
0.
#3087500
1.
0,
#3093750
0.
#3100000
1.
1,
#3106250
0.
#3112500
1.
0,
#3118750
0.
#3125000
1.
1,
#3127500
0-
#3131250
0.
#3137500
1.
0,
#3143750
0.
#3150000
1.
1,
#3156250
0.
#3162500
1.
0,
#3168750
0.
#3175000
1.
1,
#3181250
0.
#3187500
1.
0,
#3193750
0.
#3197000
b11000 8
1-
#3200000
1.
1,
#3206250
0.
#3212500
1.
0,
#3218750
0.
#3225000
1.
1,
#3231250
0.
#3237500
1.
0,
#3243750
0.
#3250000
1.
1,
#3256250
0.
#3262500
1.
0,
#3266500
0-
#3268750
0.
#3275000
1.
1,
#3281250
0.
#3287500
1.
0,
#3293750
0.
#3300000
1.
1,
#3306250
0.
#3312500
1.
0,
#3318750
0.
#3325000
1.
1,
#3331250
0.
#3336000
b11001 8
1-
#3337500
1.
0,
#3343750
0.
#3350000
1.
1,
#3356250
0.
#3362500
1.
0,
#3368750
0.
#3375000
1.
1,
#3381250
0.
#3387500
1.
0,
#3393750
0.
#3400000
1.
1,
#3405500
0-
#3406250
0.
#3412500
1.
0,
#3418750
0.
#3425000
1.
1,
#3431250
0.
#3437500
1.
0,
#3443750
0.
#3450000
1.
1,
#3456250
0.
#3462500
1.
0,
#3468750
0.
#3475000
b11010 8
1.
1,
1-
#3481250
0.
#3487500
1.
0,
#3493750
0.
#3500000
1.
1,
#3506250
0.
#3512500
1.
0,
#3518750
0.
#3525000
1.
1,
#3531250
0.
#3537500
1.
0,
#3543750
0.
#3544500
0-
#3550000
1.
1,
#3556250
0.
#3562500
1.
0,
#3568750
0.
#3575000
1.
1,
#3581250
0.
#3587500
1.
0,
#3593750
0.
#3600000
1.
1,
#3606250
0.
#3612500
1.
0,
#3614000
b11011 8
1-
#3618750
0.
#3625000
1.
1,
#3631250
0.
#3637500
1.
0,
#3643750
0.
#3650000
1.
1,
#3656250
0.
#3662500
1.
0,
#3668750
0.
#3675000
1.
1,
#3681250
0.
#3683500
0-
#3687500
1.
0,
#3693750
0.
#3700000
1.
1,
#3706250
0.
#3712500
1.
0,
#3718750
0.
#3725000
1.
1,
#3731250
0.
#3737500
1.
0,
#3743750
0.
#3750000
1.
1,
#3753000
b11100 8
1-
#3756250
0.
#3762500
1.
0,
#3768750
0.
#3775000
1.
1,
#3781250
0.
#3787500
1.
0,
#3793750
0.
#3800000
1.
1,
#3806250
0.
#3812500
1.
0,
#3818750
0.
#3822500
0-
#3825000
1.
1,
#3831250
0.
#3837500
1.
0,
#3843750
0.
#3850000
1.
1,
#3856250
0.
#3862500
1.
0,
#3868750
0.
#3875000
1.
1,
#3881250
0.
#3887500
1.
0,
#3892000
b11101 8
1-
#3893750
0.
#3900000
1.
1,
#3906250
0.
#3912500
1.
0,
#3918750
0.
#3925000
1.
1,
#3931250
0.
#3937500
1.
0,
#3943750
0.
#3950000
1.
1,
#3956250
0.
#3961500
0-
#3962500
1.
0,
#3968750
0.
#3975000
1.
1,
#3981250
0.
#3987500
1.
0,
#3993750
0.
#4000000
1.
1,
#4006250
0.
#4012500
1.
0,
#4018750
0.
#4025000
1.
1,
#4031000
b11110 8
1-
#4031250
0.
#4037500
1.
0,
#4043750
0.
#4050000
1.
1,
#4056250
0.
#4062500
1.
0,
#4068750
0.
#4075000
1.
1,
#4081250
0.
#4087500
1.
0,
#4093750
0.
#4100000
1.
1,
#4100500
0-
#4106250
0.
#4112500
1.
0,
#4118750
0.
#4125000
1.
1,
#4131250
0.
#4137500
1.
0,
#4143750
0.
#4150000
1.
1,
#4156250
0.
#4162500
1.
0,
#4168750
0.
#4170000
b11111 8
1-
#4175000
1.
1,
#4181250
0.
#4187500
1.
0,
#4193750
0.
#4200000
1.
1,
#4206250
0.
#4212500
1.
0,
#4218750
0.
#4225000
1.
1,
#4231250
0.
#4237500
1.
0,
#4239500
0-
#4243750
0.
#4250000
1.
1,
#4256250
0.
#4262500
1.
0,
#4268750
0.
#4275000
1.
1,
#4281250
0.
#4287500
1.
0,
#4293750
0.
#4300000
1.
1,
#4306250
0.
#4309000
b100000 8
1-
#4312500
1.
0,
#4318750
0.
#4325000
1.
1,
#4331250
0.
#4337500
1.
0,
#4343750
0.
#4350000
1.
1,
#4356250
0.
#4362500
1.
0,
#4368750
0.
#4375000
1.
1,
#4378500
0-
#4381250
0.
#4387500
1.
0,
#4393750
0.
#4400000
1.
1,
#4406250
0.
#4412500
1.
0,
#4418750
0.
#4425000
1.
1,
#4431250
0.
#4437500
1.
0,
#4443750
0.
#4448000
b100001 8
1-
#4450000
1.
1,
#4456250
0.
#4462500
1.
0,
#4468750
0.
#4475000
1.
1,
#4481250
0.
#4487500
1.
0,
#4493750
0.
#4500000
1.
1,
#4506250
0.
#4512500
1.
0,
#4517500
0-
#4518750
0.
#4525000
1.
1,
#4531250
0.
#4537500
1.
0,
#4543750
0.
#4550000
1.
1,
#4556250
0.
#4562500
1.
0,
#4568750
0.
#4575000
1.
1,
#4581250
0.
#4587000
b100010 8
1-
#4587500
1.
0,
#4593750
0.
#4600000
1.
1,
#4606250
0.
#4612500
1.
0,
#4618750
0.
#4625000
1.
1,
#4631250
0.
#4637500
1.
0,
#4643750
0.
#4650000
1.
1,
#4656250
0.
#4656500
0-
#4662500
1.
0,
#4668750
0.
#4675000
1.
1,
#4681250
0.
#4687500
1.
0,
#4693750
0.
#4700000
1.
1,
#4706250
0.
#4712500
1.
0,
#4718750
0.
#4725000
1.
1,
#4726000
b100011 8
1-
#4731250
0.
#4737500
1.
0,
#4743750
0.
#4750000
1.
1,
#4756250
0.
#4762500
1.
0,
#4768750
0.
#4775000
1.
1,
#4781250
0.
#4787500
1.
0,
#4793750
0.
#4795500
0-
#4800000
1.
1,
#4806250
0.
#4812500
1.
0,
#4818750
0.
#4825000
1.
1,
#4831250
0.
#4837500
1.
0,
#4843750
0.
#4850000
1.
1,
#4856250
0.
#4862500
1.
0,
#4865000
b100100 8
1-
#4868750
0.
#4875000
1.
1,
#4881250
0.
#4887500
1.
0,
#4893750
0.
#4900000
1.
1,
#4906250
0.
#4912500
1.
0,
#4918750
0.
#4925000
1.
1,
#4931250
0.
#4934500
0-
#4937500
1.
0,
#4943750
0.
#4950000
1.
1,
#4956250
0.
#4962500
1.
0,
#4968750
0.
#4975000
1.
1,
#4981250
0.
#4987500
1.
0,
#4993750
0.
#5000000
1.
1,
#5004000
b100101 8
1-
#5006250
0.
#5012500
1.
0,
#5018750
0.
#5025000
1.
1,
#5031250
0.
#5037500
1.
0,
#5043750
0.
#5050000
1.
1,
#5056250
0.
#5062500
1.
0,
#5068750
0.
#5073500
0-
#5075000
1.
1,
#5081250
0.
#5087500
1.
0,
#5093750
0.
#5100000
1.
1,
#5106250
0.
#5112500
1.
0,
#5118750
0.
#5125000
1.
1,
#5131250
0.
#5137500
1.
0,
#5143000
b100110 8
1-
#5143750
0.
#5150000
1.
1,
#5156250
0.
#5162500
1.
0,
#5168750
0.
#5175000
1.
1,
#5181250
0.
#5187500
1.
0,
#5193750
0.
#5200000
1.
1,
#5206250
0.
#5212500
1.
0,
0-
#5218750
0.
#5225000
1.
1,
#5231250
0.
#5237500
1.
0,
#5243750
0.
#5250000
1.
1,
#5256250
0.
#5262500
1.
0,
#5268750
0.
#5275000
1.
1,
#5281250
0.
#5282000
b100111 8
1-
#5287500
1.
0,
#5293750
0.
#5300000
1.
1,
#5306250
0.
#5312500
1.
0,
#5318750
0.
#5325000
1.
1,
#5331250
0.
#5337500
1.
0,
#5343750
0.
#5350000
1.
1,
#5351500
0-
#5356250
0.
#5362500
1.
0,
#5368750
0.
#5375000
1.
1,
#5381250
0.
#5387500
1.
0,
#5393750
0.
#5400000
1.
1,
#5406250
0.
#5412500
1.
0,
#5418750
0.
#5421000
b101000 8
1-
#5425000
1.
1,
#5431250
0.
#5437500
1.
0,
#5443750
0.
#5450000
1.
1,
#5456250
0.
#5462500
1.
0,
#5468750
0.
#5475000
1.
1,
#5481250
0.
#5487500
1.
0,
#5490500
0-
#5493750
0.
#5500000
1.
1,
#5506250
0.
#5512500
1.
0,
#5518750
0.
#5525000
1.
1,
#5531250
0.
#5537500
1.
0,
#5543750
0.
#5550000
1.
1,
#5556250
0.
#5560000
b101001 8
1-
#5562500
1.
0,
#5568750
0.
#5575000
1.
1,
#5581250
0.
#5587500
1.
0,
#5593750
0.
#5600000
1.
1,
#5606250
0.
#5612500
1.
0,
#5618750
0.
#5625000
1.
1,
#5629500
0-
#5631250
0.
#5637500
1.
0,
#5643750
0.
#5650000
1.
1,
#5656250
0.
#5662500
1.
0,
#5668750
0.
#5675000
1.
1,
#5681250
0.
#5687500
1.
0,
#5693750
0.
#5699000
b101010 8
1-
#5700000
1.
1,
#5706250
0.
#5712500
1.
0,
#5718750
0.
#5725000
1.
1,
#5731250
0.
#5737500
1.
0,
#5743750
0.
#5750000
1.
1,
#5756250
0.
#5762500
1.
0,
#5768500
0-
#5768750
0.
#5775000
1.
1,
#5781250
0.
#5787500
1.
0,
#5793750
0.
#5800000
1.
1,
#5806250
0.
#5812500
1.
0,
#5818750
0.
#5825000
1.
1,
#5831250
0.
#5837500
1.
0,
#5838000
b101011 8
1-
#5843750
0.
#5850000
1.
1,
#5856250
0.
#5862500
1.
0,
#5868750
0.
#5875000
1.
1,
#5881250
0.
#5887500
1.
0,
#5893750
0.
#5900000
1.
1,
#5906250
0.
#5907500
0-
#5912500
1.
0,
#5918750
0.
#5925000
1.
1,
#5931250
0.
#5937500
1.
0,
#5943750
0.
#5950000
1.
1,
#5956250
0.
#5962500
1.
0,
#5968750
0.
#5975000
1.
1,
#5977000
b101100 8
1-
#5981250
0.
#5987500
1.
0,
#5993750
0.
#6000000
1.
1,
#6006250
0.
#6012500
1.
0,
#6018750
0.
#6025000
1.
1,
#6031250
0.
#6037500
1.
0,
#6043750
0.
#6046500
0-
#6050000
1.
1,
#6056250
0.
#6062500
1.
0,
#6068750
0.
#6075000
1.
1,
#6081250
0.
#6087500
1.
0,
#6093750
0.
#6100000
1.
1,
#6106250
0.
#6112500
1.
0,
#6116000
b101101 8
1-
#6118750
0.
#6125000
1.
1,
#6131250
0.
#6137500
1.
0,
#6143750
0.
#6150000
1.
1,
#6156250
0.
#6162500
1.
0,
#6168750
0.
#6175000
1.
1,
#6181250
0.
#6185500
0-
#6187500
1.
0,
#6193750
0.
#6200000
1.
1,
#6206250
0.
#6212500
1.
0,
#6218750
0.
#6225000
1.
1,
#6231250
0.
#6237500
1.
0,
#6243750
0.
#6250000
1.
1,
#6255000
b101110 8
1-
#6256250
0.
#6262500
1.
0,
#6268750
0.
#6275000
1.
1,
#6281250
0.
#6287500
1.
0,
#6293750
0.
#6300000
1.
1,
#6306250
0.
#6312500
1.
0,
#6318750
0.
#6324500
0-
#6325000
1.
1,
#6331250
0.
#6337500
1.
0,
#6343750
0.
#6350000
1.
1,
#6356250
0.
#6362500
1.
0,
#6368750
0.
#6375000
1.
1,
#6381250
0.
#6387500
1.
0,
#6393750
0.
#6394000
b101111 8
1-
#6400000
1.
1,
#6406250
0.
#6412500
1.
0,
#6418750
0.
#6425000
1.
1,
#6431250
0.
#6437500
1.
0,
#6443750
0.
#6450000
1.
1,
#6456250
0.
#6462500
1.
0,
#6463500
0-
#6468750
0.
#6475000
1.
1,
#6481250
0.
#6487500
1.
0,
#6493750
0.
#6500000
1.
1,
#6506250
0.
#6512500
1.
0,
#6518750
0.
#6525000
1.
1,
#6531250
0.
#6533000
b110000 8
1-
#6537500
1.
0,
#6543750
0.
#6550000
1.
1,
#6556250
0.
#6562500
1.
0,
#6568750
0.
#6575000
1.
1,
#6581250
0.
#6587500
1.
0,
#6593750
0.
#6600000
1.
1,
#6602500
0-
#6606250
0.
#6612500
1.
0,
#6618750
0.
#6625000
1.
1,
#6631250
0.
#6637500
1.
0,
#6643750
0.
#6650000
1.
1,
#6656250
0.
#6662500
1.
0,
#6668750
0.
#6672000
b110001 8
1-
#6675000
1.
1,
#6681250
0.
#6687500
1.
0,
#6693750
0.
#6700000
1.
1,
#6706250
0.
#6712500
1.
0,
#6718750
0.
#6725000
1.
1,
#6731250
0.
#6737500
1.
0,
#6741500
0-
#6743750
0.
#6750000
1.
1,
#6756250
0.
#6762500
1.
0,
#6768750
0.
#6775000
1.
1,
#6781250
0.
#6787500
1.
0,
#6793750
0.
#6800000
1.
1,
#6806250
0.
#6811000
b110010 8
1-
#6812500
1.
0,
#6818750
0.
#6825000
1.
1,
#6831250
0.
#6837500
1.
0,
#6843750
0.
#6850000
1.
1,
#6856250
0.
#6862500
1.
0,
#6868750
0.
#6875000
1.
1,
#6880500
0-
#6881250
0.
#6887500
1.
0,
#6893750
0.
#6900000
1.
1,
#6906250
0.
#6912500
1.
0,
#6918750
0.
#6925000
1.
1,
#6931250
0.
#6937500
1.
0,
#6943750
0.
#6950000
b110011 8
1.
1,
1-
#6956250
0.
#6962500
1.
0,
