Logic/U409/U409_CIA_CYCLE.v
/*
----------------------------------------------------------------------------------
--This work is shared under the Attribution-NonCommercial-ShareAlike 4.0 International (CC BY-NC-SA 4.0) License
--https://creativecommons.org/licenses/by-nc-sa/4.0/legalcode
	
--You are free to:
--Share - copy and redistribute the material in any medium or format
--Adapt - remix, transform, and build upon the material

--Under the following terms:

--Attribution - You must give appropriate credit, provide a link to the license, and indicate if changes were made. 
--You may do so in any reasonable manner, but not in any way that suggests the licensor endorses you or your use.

--NonCommercial - You may not use the material for commercial purposes.

--ShareAlike - If you remix, transform, or build upon the material, you must distribute your contributions under the 
--same license as the original.

--No additional restrictions - You may not apply legal terms or technological measures that legally restrict others 
--from doing anything the license permits.
--------------------------------------------------------------------------------------------------------------------------------------------------------------------
-- Engineer: Jason Neus
-- 
-- Design Name: U409
-- Module Name: CIA
-- Project Name: AmigaPCI
-- Target Devices: XC95144XL 144 PIN
--
-- Description: LOGIC FOR CIA CYCLES.
--
-- Revision History:
--     05-JAN-2023 : Initial Engineering Release
----------------------------------------------------------------------------------
*/

module U409_CIA_CYCLE 
(

    input CLK40,
    input nRESET,
    input CIA_SPACE,
    input RnW,
    input nTIP,

    output reg CIA_ENABLE,  
    output reg CIA_TA,
    output PHI2

);

////////////////
// PHI2 CLOCK //
////////////////

//WE DISPOSE OF THE LEGACY E-CYCLE AS IMPLEMENTED IN ALL ORIGINAL 
//AMIGAS. INSTEAD, WE ARE USING THE TIMING FROM THE CIA DATA SHEET.
//ONE COMPLETE CIA CLOCK CYCLE IS 500ns AT 50% DUTY CYCLE.
//40MHz CLOCK = 25ns PERIOD

reg [4:0] counter = 5'b00000;
assign PHI2 = counter < 10 ? 0 : 1;

always @(negedge CLK40) begin
	counter <= counter + 1;
	if (counter == 19) begin counter <= 0; end 
end

/////////////////////
// CIA CHIP SELECT //
/////////////////////


always @(negedge CLK40 or negedge nRESET) begin

    if (!nRESET) begin
        CIA_ENABLE <= 0;
        CIA_TA <= 0;
    end else begin
        case (counter)
            0 : CIA_TA <= 0;
            1 : CIA_ENABLE <= 0;
            13 : CIA_ENABLE <= RnW && CIA_SPACE && !nTIP; //READ CYCLE CHIP ENABLE
            16 : CIA_ENABLE <= CIA_SPACE && !nTIP; //WRITE CYCLE CHIP ENABLE
            19 : CIA_TA <= CIA_ENABLE;
        endcase
    end    
end

endmodule

Logic/TestBenches/U409-TESTBENCH/CIA_CYCLE/U409_CIA_CYCLE_tb.v
// Define timescale <time unit> / <time precision>
`timescale 1 ns / 10 ps

//There are no ports in a test bench.
module cia_cycle_tb();

//reg inputs
reg CLK40 = 1;
reg RnW = 1;
reg nTIP = 1;
reg CIA_SPACE = 0;
reg nRESET = 0;
reg [4:0] counter; // = 5'b00000;

//Simulation time : 10000 * 1ns = 10us
localparam DURATION = 10000;

//Generate Clock(s)
//7.16MHz = 139ns
//40MHz = 25ns
//80MHz = 12.5ns

always #12.5 CLK40 = ~CLK40;

//THE TEST
initial begin
	#100 nRESET = 1;
    #300 CIA_SPACE = 1; nTIP = 0;
    #1140 RnW = 0;
    #474 CIA_SPACE = 0; nTIP = 1; RnW = 1;
end

//Test Parameters
initial begin
	$dumpfile("cia_cycle_tb.vcd");
	$dumpvars(0, cia_cycle_tb); //0=most verbose
	//$monitor($time,,CLK40);
	//$monitor($time,,counter);
	
	#(DURATION)
	$display("Finished");
	$finish;	
end

//Instantiate the device under test
U409_CIA_CYCLE dut
(
    .CLK40 (CLK40),
    .nRESET (nRESET),
    .CIA_SPACE (CIA_SPACE),
    .RnW (RnW),
    .nTIP (nTIP),
    .CIA_ENABLE (CIA_ENABLE),  
    .CIA_TA (CIA_TA),
    .PHI2 (PHI2)
);

endmodule

Logic/TestBenches/U409-TESTBENCH/CIA_CYCLE/cia_cycle_tb.vcd
$date
	Fri Mar  1 16:57:08 2024
$end
$version
	Icarus Verilog
$end
$timescale
	1ps
$end
$scope module cia_cycle_tb $end
$var wire 1 ! PHI2 $end
$var wire 1 " CIA_TA $end
$var wire 1 # CIA_ENABLE $end
$var reg 1 $ CIA_SPACE $end
$var reg 1 % CLK40 $end
$var reg 1 & RnW $end
$var reg 1 ' nRESET $end
$var reg 1 ( nTIP $end
$scope module dut $end
$var wire 1 $ CIA_SPACE $end
$var wire 1 % CLK40 $end
$var wire 1 & RnW $end
$var wire 1 ' nRESET $end
$var wire 1 ( nTIP $end
$var wire 1 ! PHI2 $end
$var reg 1 # CIA_ENABLE $end
$var reg 1 " CIA_TA $end
$var reg 5 ) counter [4:0] $end
$upscope $end
$upscope $end
$enddefinitions $end
#0
$dumpvars
b0 )
1(
0'
1&
1%
0$
0#
0"
0!
$end
#12500
b1 )
0%
#25000
1%
#37500
b10 )
0%
#50000
1%
#62500
b11 )
0%
#75000
1%
#87500
b100 )
0%
#100000
1%
1'
#112500
b101 )
0%
#125000
1%
#137500
b110 )
0%
#150000
1%
#162500
b111 )
0%
#175000
1%
#187500
b1000 )
0%
#200000
1%
#212500
b1001 )
0%
#225000
1%
#237500
1!
b1010 )
0%
#250000
1%
#262500
b1011 )
0%
#275000
1%
#287500
b1100 )
0%
#300000
1%
#312500
b1101 )
0%
#325000
1%
#337500
b1110 )
0%
#350000
1%
#362500
b1111 )
0%
#375000
1%
#387500
b10000 )
0%
#400000
1%
0(
1$
#412500
1#
b10001 )
0%
#425000
1%
#437500
b10010 )
0%
#450000
1%
#462500
b10011 )
0%
#475000
1%
#487500
0!
1"
b0 )
0%
#500000
1%
#512500
0"
b1 )
0%
#525000
1%
#537500
0#
b10 )
0%
#550000
1%
#562500
b11 )
0%
#575000
1%
#587500
b100 )
0%
#600000
1%
#612500
b101 )
0%
#625000
1%
#637500
b110 )
0%
#650000
1%
#662500
b111 )
0%
#675000
1%
#687500
b1000 )
0%
#700000
1%
#712500
b1001 )
0%
#725000
1%
#737500
1!
b1010 )
0%
#750000
1%
#762500
b1011 )
0%
#775000
1%
#787500
b1100 )
0%
#800000
1%
#812500
b1101 )
0%
#825000
1%
#837500
1#
b1110 )
0%
#850000
1%
#862500
b1111 )
0%
#875000
1%
#887500
b10000 )
0%
#900000
1%
#912500
b10001 )
0%
#925000
1%
#937500
b10010 )
0%
#950000
1%
#962500
b10011 )
0%
#975000
1%
#987500
0!
1"
b0 )
0%
#1000000
1%
#1012500
0"
b1 )
0%
#1025000
1%
#1037500
0#
b10 )
0%
#1050000
1%
#1062500
b11 )
0%
#1075000
1%
#1087500
b100 )
0%
#1100000
1%
#1112500
b101 )
0%
#1125000
1%
#1137500
b110 )
0%
#1150000
1%
#1162500
b111 )
0%
#1175000
1%
#1187500
b1000 )
0%
#1200000
1%
#1212500
b1001 )
0%
#1225000
1%
#1237500
1!
b1010 )
0%
#1250000
1%
#1262500
b1011 )
0%
#1275000
1%
#1287500
b1100 )
0%
#1300000
1%
#1312500
b1101 )
0%
#1325000
1%
#1337500
1#
b1110 )
0%
#1350000
1%
#1362500
b1111 )
0%
#1375000
1%
#1387500
b10000 )
0%
#1400000
1%
#1412500
b10001 )
0%
#1425000
1%
#1437500
b10010 )
0%
#1450000
1%
#1462500
b10011 )
0%
#1475000
1%
#1487500
0!
1"
b0 )
0%
#1500000
1%
#1512500
0"
b1 )
0%
#1525000
1%
#1537500
0#
b10 )
0%
#1540000
0&
#1550000
1%
#1562500
b11 )
0%
#1575000
1%
#1587500
b100 )
0%
#1600000
1%
#1612500
b101 )
0%
#1625000
1%
#1637500
b110 )
0%
#1650000
1%
#1662500
b111 )
0%
#1675000
1%
#1687500
b1000 )
0%
#1700000
1%
#1712500
b1001 )
0%
#1725000
1%
#1737500
1!
b1010 )
0%
#1750000
1%
#1762500
b1011 )
0%
#1775000
1%
#1787500
b1100 )
0%
#1800000
1%
#1812500
b1101 )
0%
#1825000
1%
#1837500
b1110 )
0%
#1850000
1%
#1862500
b1111 )
0%
#1875000
1%
#1887500
b10000 )
0%
#1900000
1%
#1912500
1#
b10001 )
0%
#1925000
1%
#1937500
b10010 )
0%
#1950000
1%
#1962500
b10011 )
0%
#1975000
1%
#1987500
0!
1"
b0 )
0%
#2000000
1%
#2012500
0"
b1 )
0%
#2014000
1&
1(
0$
#2025000
1%
#2037500
0#
b10 )
0%
#2050000
1%
#2062500
b11 )
0%
#2075000
1%
#2087500
b100 )
0%
#2100000
1%
#2112500
b101 )
0%
#2125000
1%
#2137500
b110 )
0%
#2150000
1%
#2162500
b111 )
0%
#2175000
1%
#2187500
b1000 )
0%
#2200000
1%
#2212500
b1001 )
0%
#2225000
1%
#2237500
1!
b1010 )
0%
#2250000
1%
#2262500
b1011 )
0%
#2275000
1%
#2287500
b1100 )
0%
#2300000
1%
#2312500
b1101 )
0%
#2325000
1%
#2337500
b1110 )
0%
#2350000
1%
#2362500
b1111 )
0%
#2375000
1%
#2387500
b10000 )
0%
#2400000
1%
#2412500
b10001 )
0%
#2425000
1%
#2437500
b10010 )
0%
#2450000
1%
#2462500
b10011 )
0%
#2475000
1%
#2487500
0!
b0 )
0%
#2500000
1%
#2512500
b1 )
0%
#2525000
1%
#2537500
b10 )
0%
#2550000
1%
#2562500
b11 )
0%
#2575000
1%
#2587500
b100 )
0%
#2600000
1%
#2612500
b101 )
0%
#2625000
1%
#2637500
b110 )
0%
#2650000
1%
#2662500
b111 )
0%
#2675000
1%
#2687500
b1000 )
0%
#2700000
1%
#2712500
b1001 )
0%
#2725000
1%
#2737500
1!
b1010 )
0%
#2750000
1%
#2762500
b1011 )
0%
#2775000
1%
#2787500
b1100 )
0%
#2800000
1%
#2812500
b1101 )
0%
#2825000
1%
#2837500
b1110 )
0%
#2850000
1%
#2862500
b1111 )
0%
#2875000
1%
#2887500
b10000 )
0%
#2900000
1%
#2912500
b10001 )
0%
#2925000
1%
#2937500
b10010 )
0%
#2950000
1%
#2962500
b10011 )
0%
#2975000
1%
#2987500
0!
b0 )
0%
#3000000
1%
#3012500
b1 )
0%
#3025000
1%
#3037500
b10 )
0%
#3050000
1%
#3062500
b11 )
0%
#3075000
1%
#3087500
b100 )
0%
#3100000
1%
#3112500
b101 )
0%
#3125000
1%
#3137500
b110 )
0%
#3150000
1%
#3162500
b111 )
0%
#3175000
1%
#3187500
b1000 )
0%
#3200000
1%
#3212500
b1001 )
0%
#3225000
1%
#3237500
1!
b1010 )
0%
#3250000
1%
#3262500
b1011 )
0%
#3275000
1%
#3287500
b1100 )
0%
#3300000
1%
#3312500
b1101 )
0%
#3325000
1%
#3337500
b1110 )
0%
#3350000
1%
#3362500
b1111 )
0%
#3375000
1%
#3387500
b10000 )
0%
#3400000
1%
#3412500
b10001 )
0%
#3425000
1%
#3437500
b10010 )
0%
#3450000
1%
#3462500
b10011 )
0%
#3475000
1%
#3487500
0!
b0 )
0%
#3500000
1%
#3512500
b1 )
0%
#3525000
1%
#3537500
b10 )
0%
#3550000
1%
#3562500
b11 )
0%
#3575000
1%
#3587500
b100 )
0%
#3600000
1%
#3612500
b101 )
0%
#3625000
1%
#3637500
b110 )
0%
#3650000
1%
#3662500
b111 )
0%
#3675000
1%
#3687500
b1000 )
0%
#3700000
1%
#3712500
b1001 )
0%
#3725000
1%
#3737500
1!
b1010 )
0%
#3750000
1%
#3762500
b1011 )
0%
#3775000
1%
#3787500
b1100 )
0%
#3800000
1%
#3812500
b1101 )
0%
#3825000
1%
#3837500
b1110 )
0%
#3850000
1%
#3862500
b1111 )
0%
#3875000
1%
#3887500
b10000 )
0%
#3900000
1%
#3912500
b10001 )
0%
#3925000
1%
#3937500
b10010 )
0%
#3950000
1%
#3962500
b10011 )
0%
#3975000
1%
#3987500
0!
b0 )
0%
#4000000
1%
#4012500
b1 )
0%
#4025000
1%
#4037500
b10 )
0%
#4050000
1%
#4062500
b11 )
0%
#4075000
1%
#4087500
b100 )
0%
#4100000
1%
#4112500
b101 )
0%
#4125000
1%
#4137500
b110 )
0%
#4150000
1%
#4162500
b111 )
0%
#4175000
1%
#4187500
b1000 )
0%
#4200000
1%
#4212500
b1001 )
0%
#4225000
1%
#4237500
1!
b1010 )
0%
#4250000
1%
#4262500
b1011 )
0%
#4275000
1%
#4287500
b1100 )
0%
#4300000
1%
#4312500
b1101 )
0%
#4325000
1%
#4337500
b1110 )
0%
#4350000
1%
#4362500
b1111 )
0%
#4375000
1%
#4387500
b10000 )
0%
#4400000
1%
#4412500
b10001 )
0%
#4425000
1%
#4437500
b10010 )
0%
#4450000
1%
#4462500
b10011 )
0%
#4475000
1%
#4487500
0!
b0 )
0%
#4500000
1%
#4512500
b1 )
0%
#4525000
1%
#4537500
b10 )
0%
#4550000
1%
#4562500
b11 )
0%
#4575000
1%
#4587500
b100 )
0%
#4600000
1%
#4612500
b101 )
0%
#4625000
1%
#4637500
b110 )
0%
#4650000
1%
#4662500
b111 )
0%
#4675000
1%
#4687500
b1000 )
0%
#4700000
1%
#4712500
b1001 )
0%
#4725000
1%
#4737500
1!
b1010 )
0%
#4750000
1%
#4762500
b1011 )
0%
#4775000
1%
#4787500
b1100 )
0%
#4800000
1%
#4812500
b1101 )
0%
#4825000
1%
#4837500
b1110 )
0%
#4850000
1%
#4862500
b1111 )
0%
#4875000
1%
#4887500
b10000 )
0%
#4900000
1%
#4912500
b10001 )
0%
#4925000
1%
#4937500
b10010 )
0%
#4950000
1%
#4962500
b10011 )
0%
#4975000
1%
#4987500
0!
b0 )
0%
#5000000
1%
#5012500
b1 )
0%
#5025000
1%
#5037500
b10 )
0%
#5050000
1%
#5062500
b11 )
0%
#5075000
1%
#5087500
b100 )
0%
#5100000
1%
#5112500
b101 )
0%
#5125000
1%
#5137500
b110 )
0%
#5150000
1%
#5162500
b111 )
0%
#5175000
1%
#5187500
b1000 )
0%
#5200000
1%
#5212500
b1001 )
0%
#5225000
1%
#5237500
1!
b1010 )
0%
#5250000
1%
#5262500
b1011 )
0%
#5275000
1%
#5287500
b1100 )
0%
#5300000
1%
#5312500
b1101 )
0%
#5325000
1%
#5337500
b1110 )
0%
#5350000
1%
#5362500
b1111 )
0%
#5375000
1%
#5387500
b10000 )
0%
#5400000
1%
#5412500
b10001 )
0%
#5425000
1%
#5437500
b10010 )
0%
#5450000
1%
#5462500
b10011 )
0%
#5475000
1%
#5487500
0!
b0 )
0%
#5500000
1%
#5512500
b1 )
0%
#5525000
1%
#5537500
b10 )
0%
#5550000
1%
#5562500
b11 )
0%
#5575000
1%
#5587500
b100 )
0%
#5600000
1%
#5612500
b101 )
0%
#5625000
1%
#5637500
b110 )
0%
#5650000
1%
#5662500
b111 )
0%
#5675000
1%
#5687500
b1000 )
0%
#5700000
1%
#5712500
b1001 )
0%
#5725000
1%
#5737500
1!
b1010 )
0%
#5750000
1%
#5762500
b1011 )
0%
#5775000
1%
#5787500
b1100 )
0%
#5800000
1%
#5812500
b1101 )
0%
#5825000
1%
#5837500
b1110 )
0%
#5850000
1%
#5862500
b1111 )
0%
#5875000
1%
#5887500
b10000 )
0%
#5900000
1%
#5912500
b10001 )
0%
#5925000
1%
#5937500
b10010 )
0%
#5950000
1%
#5962500
b10011 )
0%
#5975000
1%
#5987500
0!
b0 )
0%
#6000000
1%
#6012500
b1 )
0%
#6025000
1%
#6037500
b10 )
0%
#6050000
1%
#6062500
b11 )
0%
#6075000
1%
#6087500
b100 )
0%
#6100000
1%
#6112500
b101 )
0%
#6125000
1%
#6137500
b110 )
0%
#6150000
1%
#6162500
b111 )
0%
#6175000
1%
#6187500
b1000 )
0%
#6200000
1%
#6212500
b1001 )
0%
#6225000
1%
#6237500
1!
b1010 )
0%
#6250000
1%
#6262500
b1011 )
0%
#6275000
1%
#6287500
b1100 )
0%
#6300000
1%
#6312500
b1101 )
0%
#6325000
1%
#6337500
b1110 )
0%
#6350000
1%
#6362500
b1111 )
0%
#6375000
1%
#6387500
b10000 )
0%
#6400000
1%
#6412500
b10001 )
0%
#6425000
1%
#6437500
b10010 )
0%
#6450000
1%
#6462500
b10011 )
0%
#6475000
1%
#6487500
0!
b0 )
0%
#6500000
1%
#6512500
b1 )
0%
#6525000
1%
#6537500
b10 )
0%
#6550000
1%
#6562500
b11 )
0%
#6575000
1%
#6587500
b100 )
0%
#6600000
1%
#6612500
b101 )
0%
#6625000
1%
#6637500
b110 )
0%
#6650000
1%
#6662500
b111 )
0%
#6675000
1%
#6687500
b1000 )
0%
#6700000
1%
#6712500
b1001 )
0%
#6725000
1%
#6737500
1!
b1010 )
0%
#6750000
1%
#6762500
b1011 )
0%
#6775000
1%
#6787500
b1100 )
0%
#6800000
1%
#6812500
b1101 )
0%
#6825000
1%
#6837500
b1110 )
0%
#6850000
1%
#6862500
b1111 )
0%
#6875000
1%
#6887500
b10000 )
0%
#6900000
1%
#6912500
b10001 )
0%
#6925000
1%
#6937500
b10010 )
0%
#6950000
1%
#6962500
b10011 )
0%
#6975000
1%
#6987500
0!
b0 )
0%
#7000000
1%
#7012500
b1 )
0%
#7025000
1%
#7037500
b10 )
0%
#7050000
1%
#7062500
b11 )
0%
#7075000
1%
#7087500
b100 )
0%
#7100000
1%
#7112500
b101 )
0%
#7125000
1%
#7137500
b110 )
0%
#7150000
1%
#7162500
b111 )
0%
#7175000
1%
#7187500
b1000 )
0%
#7200000
1%
#7212500
b1001 )
0%
#7225000
1%
#7237500
1!
b1010 )
0%
#7250000
1%
#7262500
b1011 )
0%
#7275000
1%
#7287500
b1100 )
0%
#7300000
1%
#7312500
b1101 )
0%
#7325000
1%
#7337500
b1110 )
0%
#7350000
1%
#7362500
b1111 )
0%
#7375000
1%
#7387500
b10000 )
0%
#7400000
1%
#7412500
b10001 )
0%
#7425000
1%
#7437500
b10010 )
0%
#7450000
1%
#7462500
b10011 )
0%
#7475000
1%
#7487500
0!
b0 )
0%
#7500000
1%
#7512500
b1 )
0%
#7525000
1%
#7537500
b10 )
0%
#7550000
1%
#7562500
b11 )
0%
#7575000
1%
#7587500
b100 )
0%
#7600000
1%
#7612500
b101 )
0%
#7625000
1%
#7637500
b110 )
0%
#7650000
1%
#7662500
b111 )
0%
#7675000
1%
#7687500
b1000 )
0%
#7700000
1%
#7712500
b1001 )
0%
#7725000
1%
#7737500
1!
b1010 )
0%
#7750000
1%
#7762500
b1011 )
0%
#7775000
1%
#7787500
b1100 )
0%
#7800000
1%
#7812500
b1101 )
0%
#7825000
1%
#7837500
b1110 )
0%
#7850000
1%
#7862500
b1111 )
0%
#7875000
1%
#7887500
b10000 )
0%
#7900000
1%
#7912500
b10001 )
0%
#7925000
1%
#7937500
b10010 )
0%
#7950000
1%
#7962500
b10011 )
0%
#7975000
1%
#7987500
0!
b0 )
0%
#8000000
1%
#8012500
b1 )
0%
#8025000
1%
#8037500
b10 )
0%
#8050000
1%
#8062500
b11 )
0%
#8075000
1%
#8087500
b100 )
0%
#8100000
1%
#8112500
b101 )
0%
#8125000
1%
#8137500
b110 )
0%
#8150000
1%
#8162500
b111 )
0%
#8175000
1%
#8187500
b1000 )
0%
#8200000
1%
#8212500
b1001 )
0%
#8225000
1%
#8237500
1!
b1010 )
0%
#8250000
1%
#8262500
b1011 )
0%
#8275000
1%
#8287500
b1100 )
0%
#8300000
1%
#8312500
b1101 )
0%
#8325000
1%
#8337500
b1110 )
0%
#8350000
1%
#8362500
b1111 )
0%
#8375000
1%
#8387500
b10000 )
0%
#8400000
1%
#8412500
b10001 )
0%
#8425000
1%
#8437500
b10010 )
0%
#8450000
1%
#8462500
b10011 )
0%
#8475000
1%
#8487500
0!
b0 )
0%
#8500000
1%
#8512500
b1 )
0%
#8525000
1%
#8537500
b10 )
0%
#8550000
1%
#8562500
b11 )
0%
#8575000
1%
#8587500
b100 )
0%
#8600000
1%
#8612500
b101 )
0%
#8625000
1%
#8637500
b110 )
0%
#8650000
1%
#8662500
b111 )
0%
#8675000
1%
#8687500
b1000 )
0%
#8700000
1%
#8712500
b1001 )
0%
#8725000
1%
#8737500
1!
b1010 )
0%
#8750000
1%
#8762500
b1011 )
0%
#8775000
1%
#8787500
b1100 )
0%
#8800000
1%
#8812500
b1101 )
0%
#8825000
1%
#8837500
b1110 )
0%
#8850000
1%
#8862500
b1111 )
0%
#8875000
1%
#8887500
b10000 )
0%
#8900000
1%
#8912500
b10001 )
0%
#8925000
1%
#8937500
b10010 )
0%
#8950000
1%
#8962500
b10011 )
0%
#8975000
1%
#8987500
0!
b0 )
0%
#9000000
1%
#9012500
b1 )
0%
#9025000
1%
#9037500
b10 )
0%
#9050000
1%
#9062500
b11 )
0%
#9075000
1%
#9087500
b100 )
0%
#9100000
1%
#9112500
b101 )
0%
#9125000
1%
#9137500
b110 )
0%
#9150000
1%
#9162500
b111 )
0%
#9175000
1%
#9187500
b1000 )
0%
#9200000
1%
#9212500
b1001 )
0%
#9225000
1%
#9237500
1!
b1010 )
0%
#9250000
1%
#9262500
b1011 )
0%
#9275000
1%
#9287500
b1100 )
0%
#9300000
1%
#9312500
b1101 )
0%
#9325000
1%
#9337500
b1110 )
0%
#9350000
1%
#9362500
b1111 )
0%
#9375000
1%
#9387500
b10000 )
0%
#9400000
1%
#9412500
b10001 )
0%
#9425000
1%
#9437500
b10010 )
0%
#9450000
1%
#9462500
b10011 )
0%
#9475000
1%
#9487500
0!
b0 )
0%
#9500000
1%
#9512500
b1 )
0%
#9525000
1%
#9537500
b10 )
0%
#9550000
1%
#9562500
b11 )
0%
#9575000
1%
#9587500
b100 )
0%
#9600000
1%
#9612500
b101 )
0%
#9625000
1%
#9637500
b110 )
0%
#9650000
1%
#9662500
b111 )
0%
#9675000
1%
#9687500
b1000 )
0%
#9700000
1%
#9712500
b1001 )
0%
#9725000
1%
#9737500
1!
b1010 )
0%
#9750000
1%
#9762500
b1011 )
0%
#9775000
1%
#9787500
b1100 )
0%
#9800000
1%
#9812500
b1101 )
0%
#9825000
1%
#9837500
b1110 )
0%
#9850000
1%
#9862500
b1111 )
0%
#9875000
1%
#9887500
b10000 )
0%
#9900000
1%
#9912500
b10001 )
0%
#9925000
1%
#9937500
b10010 )
0%
#9950000
1%
#9962500
b10011 )
0%
#9975000
1%
#9987500
0!
b0 )
0%
