Logic/U109/U109_FIFO_WRITE.v
//////////////////////////////////////////////////////////////////////////////////
//This work is shared under the Attribution/NonCommercial/ShareAlike 4.0 International (CC BY/NC/SA 4.0) License
//https://creativecommons.org/licenses/by/nc/sa/4.0/legalcode
//	
//You are free to:
//Share - copy and redistribute the material in any medium or format
//Adapt - remix, transform, and build upon the material
//
//Under the following terms:
//
//Attribution - You must give appropriate credit, provide a link to the license, and indicate if changes were made. 
//You may do so in any reasonable manner, but not in any way that suggests the licensor endorses you or your use.
//
//NonCommercial - You may not use the material for commercial purposes.
//
//ShareAlike - If you remix, transform, or build upon the material, you must distribute your contributions under the 
//same license as the original.
//
//No additional restrictions - You may not apply legal terms or technological measures that legally restrict others 
//from doing anything the license permits.
///////////////////////////////////////////////////////////////////////////////////
// Engineer: Jason Neus
// 
// Design Name: U109
// Module Name: U109_FIFO
// Project Name: AmigaPCI
// Target Devices: iCE40-HX4K-TQ144
//
// Description: WRITE DATA TO FIFO
//
// Revision History:
//     xx-xxx-2024 : Initial Engineering Release
///////////////////////////////////////////////////////////////////////////////////

module U109_FIFO (

    input PCLK, PCICLK, BCLK,
    input nRESET,
    input [31:0]AD,
    input [31:0]D,
    input PCIDIR,
    input REGCYCLE,
    input nBEN,
    input nTA, nTRDY, nIRDY, nBG,

    output [31:0] DATA_OUT,
    output EMPTY

);

////////////////////
// FIFO RAM SPACE //
////////////////////

//THE BLOCK RAM OF THE HX4K IS 256x16 (4k).

parameter DEPTH = 16; //FIFO DEPTH. 16 WILL HOLD TWO BURST CYCLES, 24 HOLDS 3 BURST CYCLES, ETC. AT 4 WORDS PER BURST
parameter DATA_WIDTH = 16; //DATA BUS WIDTH
parameter PTR_SIZE = 4; //ADDRESS BUS IS 5 BITS

reg [DEPTH-1:0] MEMORY [0:DATA_WIDTH-1]; //2D ARRAY. 16 ADDRESS DEEP x 2 BYTES WIDE
reg [PTR_SIZE-1:0] WR_POINTER;
reg [PTR_SIZE-1:0] RD_POINTER;

//////////////////
// SYNCHRONIZER //
//////////////////

reg [1:0] PCICLK_SAMP;
reg [1:0] BCLK_SAMP;

always @(posedge PCLK, negedge nRESET) begin
    if (!nRESET) begin
        PCICLK_SAMP <= 2'b11;
        BCLK_SAMP <= 2'b11;
    end else begin
        PCICLK_SAMP <= {PCICLK_SAMP[0] , PCICLK}; 
        BCLK_SAMP <= {BCLK_SAMP[0] , BCLK}; 
    end
end

///////////////////////
// FIFO FILL PROCESS //
///////////////////////

//WE FILL THE FIFO FROM THE AMIGA DURING CPU WRITE CYCLES OR DMA READ CYCLES.
//WE FILL THE FIFO FROM THE PCI BUS DURING CPU READ CYCLES OR DMA WRITE CYCLES.
//BRIDGE REGISTER CYCLES DO NOT USE FIFO.

//BOTH THE PCI AND AMIGA (MOTOROLA) BUSSES LATCH DATA ON THE RISING CLOCK EDGE.

integer i;
wire WRITE_EN;
wire [31:0] DATA_IN;

assign WRITE_EN = !REGCYCLE && !nBEN && ((PCIDIR && !nTA) || (!PCIDIR && ((!nBG && !nTRDY) || (nBG && !nIRDY))));
assign DATA_IN = PCIDIR ? D : AD;

//WRITE DATA TO THE FIFO
always @(negedge PCLK, negedge nRESET) begin
    if (!nRESET) begin
        for (i=0; i<DEPTH-1; i=i+1) MEMORY[i] <= 16'h0;
        WR_POINTER <= 0;
    end else if (WRITE_EN) begin
        if ((PCIDIR && BCLK_SAMP == 2'b01) || (!PCIDIR && PCICLK_SAMP == 2'b01)) begin
            MEMORY[WR_POINTER] <= DATA_IN[31:16];
            MEMORY[WR_POINTER + 1] <= DATA_IN[15:0];
            WR_POINTER <= WR_POINTER + 2;
        end
    end
end

////////////////////
// READ FROM FIFO //
////////////////////

wire READ_EN;
assign READ_EN = !REGCYCLE && (PCIDIR && !nTRDY); //&& !nBEN 
assign EMPTY = RD_POINTER == WR_POINTER ? 1 : 0;

always @(negedge PCLK, negedge nRESET) begin
    if (!nRESET) begin
        RD_POINTER <= 0;
    end else if (READ_EN || !EMPTY) begin
        if ((!PCIDIR && BCLK_SAMP == 2'b10) || (PCIDIR && PCICLK_SAMP == 2'b01)) begin
            RD_POINTER = RD_POINTER + 2;
        end 
    end
end

assign DATA_OUT = !EMPTY ? {MEMORY[RD_POINTER], MEMORY[RD_POINTER + 1]} : 32'h0;

///////////////
// FULL FIFO //
///////////////

//SET THE FULL REGISTER SIGNAL

/*reg FULL;

always @(negedge PCLK, negedge nRESET)
begin
	if (!nRESET)
		FULL <= 0;
	else if (WRITE_EN && WR_POINTER == RD_POINTER)
		FULL <= 1;
	else if (READ_EN && !EMPTY)
		FULL <= 0;
end*/

endmodule

Logic/U109/U109_TOP.v
//////////////////////////////////////////////////////////////////////////////////
//This work is shared under the Attribution/NonCommercial/ShareAlike 4.0 International (CC BY/NC/SA 4.0) License
//https://creativecommons.org/licenses/by/nc/sa/4.0/legalcode
//	
//You are free to:
//Share - copy and redistribute the material in any medium or format
//Adapt - remix, transform, and build upon the material
//
//Under the following terms:
//
//Attribution - You must give appropriate credit, provide a link to the license, and indicate if changes were made. 
//You may do so in any reasonable manner, but not in any way that suggests the licensor endorses you or your use.
//
//NonCommercial - You may not use the material for commercial purposes.
//
//ShareAlike - If you remix, transform, or build upon the material, you must distribute your contributions under the 
//same license as the original.
//
//No additional restrictions - You may not apply legal terms or technological measures that legally restrict others 
//from doing anything the license permits.
///////////////////////////////////////////////////////////////////////////////////
// Engineer: Jason Neus
// 
// Design Name: U109
// Module Name: U109_TOP
// Project Name: AmigaPCI
// Target Devices: iCE40-HX4K-TQ144
//
// Description: PCI FIFO, AD BUFFERS
//
// Revision History:
//     xx-xxx-2024 : Initial Engineering Release
///////////////////////////////////////////////////////////////////////////////////

//TO BUILD WITH APIO: apio build --top-module U109_TOP --fpga iCE40-HX4K-TQ144

module U109_TOP (

    input PCLK, PCICLK, BCLK,
    input nRESET, TT0, TT1,
    inout [31:0]AD,
    inout [31:0]D,
    input PCIDIR,
    input nBEN,
    input nTRDY, nIRDY, nBG, nTS,

    output nTA

);

// BRIDGE REGISTER CYCLE //

wire REGCYCLE; 
assign REGCYCLE = 0; //.fix this later

//////////////////////////
// MC68040 TRANSFER ACK //
//////////////////////////
wire TA;
wire TA_SPACE;
reg FIFO_TA;
reg TA_CYCLE;
reg TS;

assign TA = FIFO_TA;
assign TA_SPACE = !nBEN;
assign nTA = TA ? 1'b0 : TA_SPACE || TA_CYCLE ? 1'b1 : 1'bZ;

//TA_CYCLE FORCES _TA HIGH AFTER NEGATION TO PREVENT IT INADVERTENTLY
//ENDING THE NEXT CYCLE PREMATURELY.
always @(posedge BCLK, negedge nRESET) begin
    if (!nRESET) begin
        TA_CYCLE <= 0;
    end else begin

        TS <= ~nTS;

        if (!nTA && TA_SPACE) begin
            TA_CYCLE <= 1; end 
        else begin
            TA_CYCLE <= 0; 
        end
    end
end

//ASSERT _TA ON CPU DRIVEN CYCLES
reg [1:0]TA_COUNT;
wire BURST_CYCLE;
assign BURST_CYCLE = TT0 && !TT1;

always @(negedge BCLK, negedge nRESET) begin
    if (!nRESET) begin
        FIFO_TA <= 0;
        TA_COUNT <= 2'b00;
    end else begin
        case (TA_COUNT) 
            2'b00: if (TS && !nBG) begin FIFO_TA <= 1; TA_COUNT <= 2'b01; end else begin FIFO_TA <= 0; end
            2'b01: if (!BURST_CYCLE) begin FIFO_TA <= 0; TA_COUNT <= 2'b00; end else begin TA_COUNT <= 2'b10; end
            2'b10: TA_COUNT <= 2'b11;
            2'b11: TA_COUNT <= 2'b00;
        endcase
    end
end

/////////////////
// DATA OUTPUT //
/////////////////

wire PCICYCLE;
wire [31:0]DATA_OUTm;
assign D = !nBEN && !PCIDIR ? DATA_OUTm : 'bz;
assign AD = (!nBEN || !EMPTY) && PCIDIR ? DATA_OUTm : 'bz; //IF THE FIFO IS NOT EMPTY, KEEP THE CYCLE GOING UNTIL IT IS.

//////////
// FIFO //
//////////

U109_FIFO U109_FIFO (

    .PCLK (PCLK),
    .PCICLK (PCICLK),
    .BCLK (BCLK),
    .nRESET (nRESET),
    .AD (AD),
    .D (D),
    .PCIDIR (PCIDIR),
    .REGCYCLE (REGCYCLE),
    .nBEN (nBEN),
    .nTA (nTA),
    .nTRDY (nTRDY),
    .nIRDY (nIRDY),
    .nBG (nBG),
    .DATA_OUT (DATA_OUTm),
    .EMPTY (EMPTY)

);



endmodule

Logic/U109/U109_TOP_TB.v
// Define timescale <time unit> / <time precision>
`timescale 1 ns / 10 ps
`default_nettype none

//There are no ports in a test bench.
module top_tb();

//inputs
reg BCLK = 1;
reg PCLK = 1;
reg PCICLK = 1;
reg nRESET = 0;
reg PCIDIR = 0;
reg nBEN = 1;
reg nTS = 1;
reg nTRDY = 1;
reg nIRDY = 1;
reg nBG = 0;
reg TT0 = 1;
reg TT1 = 0;
wire [31:0] D = 'bz;
wire [31:0] AD = 'bz;
reg REGCYCLE = 0;

//wire outputs
wire [31:0] DATA_OUT;
//reg [1:0] i;
reg [31:0] DData = 'bz;
reg [31:0] ADData = 'bz;

assign D = DData;
assign AD = ADData;

//Simulation time : 10000 * 1ns = 10us
localparam DURATION = 10000;

//Generate Clock(s)
always #16.66667 PCICLK = ~PCICLK;
always #12.5 BCLK = ~BCLK;
always #6.25 PCLK = ~PCLK;

//THE TEST
initial begin
	#100 nRESET = 1;

    //CPU CYCLE WRITE
    /*#137.5 nBEN = 0; PCIDIR = 1; nTS = 0; DData = 32'hffff0000; //set cpu signals
    #25    nTS = 1;
    #21.5  nTRDY = 0; //wait for pci target ready
    #3.5   DData = 32'heeee1111;    
    #25    DData = 32'hdddd2222;
    #25    DData = 32'hcccc3333;
    #25    DData = 'bz; nBEN = 1;
    #53    nTRDY = 1;*/

    #137.5 nBEN = 0; PCIDIR = 1; nTS = 0; DData = 32'hffff0000; //set cpu signals
    #25    nTS = 1;
    #21.5  nTRDY = 0; //wait for pci target ready
    #3.5   DData = 32'heeee1111;    
    #25    DData = 32'hdddd2222;
    #25    DData = 32'hcccc3333;
    #25    DData = 'bz; nBEN = 1;
    #53    nTRDY = 1;

    #22 nBEN = 0; PCIDIR = 1; nTS = 0; DData = 32'hffff0000; //set cpu signals
    #25    nTS = 1;
    #21.5  nTRDY = 0; //wait for pci target ready
    #3.5   DData = 32'heeee1111;    
    #25    DData = 32'hdddd2222;
    #25    DData = 32'hcccc3333;
    #25    DData = 'bz; nBEN = 1;
    #53    nTRDY = 1;
    

end

//Test Parameters
initial begin
	$dumpfile("u109_top_tb.vcd");
	$dumpvars(0, top_tb); //0=most verbose
	//$monitor($time,,AC_ADDRESS);
	//$monitor($time,,counter);
	
	#(DURATION)
	$display("Finished");
	$finish;	
end

//Instantiate the device under test
U109_TOP dut
(
    .PCLK (PCLK),
    .PCICLK (PCICLK),
    .BCLK (BCLK),
    .nRESET (nRESET),
    .AD (AD),
    .D (D),
    .PCIDIR (PCIDIR),
    .nBEN (nBEN),
    .nTS (nTS),
    .nTRDY (nTRDY),
    .nIRDY (nIRDY),
    .nBG (nBG),
    .TT0 (TT0),
    .TT1 (TT1)

);

endmodule

Logic/U109/u109_top_tb.vcd
$date
	Sun Mar 31 21:39:09 2024
$end
$version
	Icarus Verilog
$end
$timescale
	1ps
$end
$scope module top_tb $end
$var wire 32 ! AD [31:0] $end
$var wire 32 " D [31:0] $end
$var parameter 32 # DURATION $end
$var reg 32 $ ADData [31:0] $end
$var reg 1 % BCLK $end
$var reg 32 & DData [31:0] $end
$var reg 1 ' PCICLK $end
$var reg 1 ( PCIDIR $end
$var reg 1 ) PCLK $end
$var reg 1 * REGCYCLE $end
$var reg 1 + TT0 $end
$var reg 1 , TT1 $end
$var reg 1 - nBEN $end
$var reg 1 . nBG $end
$var reg 1 / nIRDY $end
$var reg 1 0 nRESET $end
$var reg 1 1 nTRDY $end
$var reg 1 2 nTS $end
$scope module dut $end
$var wire 32 3 AD [31:0] $end
$var wire 1 % BCLK $end
$var wire 1 4 BURST_CYCLE $end
$var wire 32 5 D [31:0] $end
$var wire 1 ' PCICLK $end
$var wire 1 ( PCIDIR $end
$var wire 1 ) PCLK $end
$var wire 1 6 REGCYCLE $end
$var wire 1 7 TA $end
$var wire 1 + TT0 $end
$var wire 1 , TT1 $end
$var wire 1 - nBEN $end
$var wire 1 . nBG $end
$var wire 1 / nIRDY $end
$var wire 1 0 nRESET $end
$var wire 1 1 nTRDY $end
$var wire 1 2 nTS $end
$var wire 1 8 nTA $end
$var wire 1 9 TA_SPACE $end
$var wire 1 : EMPTY $end
$var wire 32 ; DATA_OUTm [31:0] $end
$var reg 1 7 FIFO_TA $end
$var reg 2 < TA_COUNT [1:0] $end
$var reg 1 = TA_CYCLE $end
$var reg 1 > TS $end
$scope module U109_FIFO $end
$var wire 32 ? AD [31:0] $end
$var wire 1 % BCLK $end
$var wire 32 @ D [31:0] $end
$var wire 1 ' PCICLK $end
$var wire 1 ( PCIDIR $end
$var wire 1 ) PCLK $end
$var wire 1 A READ_EN $end
$var wire 1 6 REGCYCLE $end
$var wire 1 B WRITE_EN $end
$var wire 1 - nBEN $end
$var wire 1 . nBG $end
$var wire 1 / nIRDY $end
$var wire 1 0 nRESET $end
$var wire 1 8 nTA $end
$var wire 1 1 nTRDY $end
$var wire 1 : EMPTY $end
$var wire 32 C DATA_OUT [31:0] $end
$var wire 32 D DATA_IN [31:0] $end
$var parameter 32 E DATA_WIDTH $end
$var parameter 32 F DEPTH $end
$var parameter 32 G PTR_SIZE $end
$var reg 2 H BCLK_SAMP [1:0] $end
$var reg 2 I PCICLK_SAMP [1:0] $end
$var reg 4 J RD_POINTER [3:0] $end
$var reg 4 K WR_POINTER [3:0] $end
$var integer 32 L i [31:0] $end
$upscope $end
$upscope $end
$upscope $end
$enddefinitions $end
$comment Show the parameter values. $end
$dumpall
b100 G
b10000 F
b10000 E
b10011100010000 #
$end
#0
$dumpvars
b1111 L
b0 K
b0 J
b11 I
b11 H
bz D
b0 C
0B
0A
bz @
bz ?
x>
0=
b0 <
b0 ;
1:
09
z8
07
06
bz 5
14
bz 3
12
11
00
1/
0.
1-
0,
1+
0*
1)
0(
1'
bz &
1%
bz $
bz "
bz !
$end
#6250
b1111 L
0)
#12500
1)
0%
#16670
0'
#18750
b1111 L
0)
#25000
1)
1%
#31250
b1111 L
0)
#33340
1'
#37500
1)
0%
#43750
b1111 L
0)
#50000
1)
1%
#50010
0'
#56250
b1111 L
0)
#62500
1)
0%
#66680
1'
#68750
b1111 L
0)
#75000
1)
1%
#81250
b1111 L
0)
#83350
0'
#87500
1)
0%
#93750
b1111 L
0)
#100000
b10 I
0>
1)
1%
10
#100020
1'
#106250
0)
#112500
b10 H
b1 I
1)
0%
#116690
0'
#118750
0)
#125000
b1 H
b10 I
1)
1%
#131250
0)
#133360
1'
#137500
b10 H
b1 I
1)
0%
#143750
0)
#150000
b1 H
b11 I
1)
1%
#150030
0'
#156250
0)
#162500
b10 H
b10 I
1)
0%
#166700
1'
#168750
0)
#175000
b1 H
b1 I
1)
1%
#181250
0)
#183370
0'
#187500
b10 H
b10 I
1)
0%
#193750
0)
#200000
b1 H
b0 I
1)
1%
#200040
1'
#206250
0)
#212500
b10 H
b1 I
1)
0%
#216710
0'
#218750
0)
#225000
b1 H
b10 I
1)
1%
#231250
0)
#233380
1'
#237500
b10 H
b1 I
0B
18
b0 !
b0 3
b0 ?
b11111111111111110000000000000000 D
1)
0%
b11111111111111110000000000000000 "
b11111111111111110000000000000000 5
b11111111111111110000000000000000 @
b11111111111111110000000000000000 &
02
1(
19
0-
#243750
0)
#250000
b1 H
b11 I
1>
1)
1%
#250050
0'
#256250
0)
#262500
1B
08
b10 H
b10 I
b1 <
17
1)
0%
12
#266720
1'
#268750
0)
#275000
b1 H
b1 I
1=
0>
1)
1%
#281250
b11111111111111110000000000000000 !
b11111111111111110000000000000000 3
b11111111111111110000000000000000 ?
b11111111111111110000000000000000 ;
b11111111111111110000000000000000 C
0:
b10 K
0)
#283390
0'
#284000
1A
01
#287500
b10 H
b10 I
b10 <
b11101110111011100001000100010001 D
b11101110111011100001000100010001 "
b11101110111011100001000100010001 5
b11101110111011100001000100010001 @
b11101110111011100001000100010001 &
1)
0%
#293750
0)
#300000
b1 H
b0 I
1)
1%
#300060
1'
#306250
b100 K
0)
#312500
b10 H
b1 I
b11 <
b11011101110111010010001000100010 D
1)
0%
b11011101110111010010001000100010 "
b11011101110111010010001000100010 5
b11011101110111010010001000100010 @
b11011101110111010010001000100010 &
#316730
0'
#318750
b11101110111011100001000100010001 !
b11101110111011100001000100010001 3
b11101110111011100001000100010001 ?
b11101110111011100001000100010001 ;
b11101110111011100001000100010001 C
b10 J
0)
#325000
b1 H
b10 I
1)
1%
#331250
b110 K
0)
#333400
1'
#337500
b10 H
b1 I
b0 <
b11001100110011000011001100110011 D
1)
0%
b11001100110011000011001100110011 "
b11001100110011000011001100110011 5
b11001100110011000011001100110011 @
b11001100110011000011001100110011 &
#343750
b11011101110111010010001000100010 !
b11011101110111010010001000100010 3
b11011101110111010010001000100010 ?
b11011101110111010010001000100010 ;
b11011101110111010010001000100010 C
b100 J
0)
#350000
b1 H
b11 I
1)
1%
#350070
0'
#356250
b1000 K
0)
#362500
18
b10 H
b10 I
07
0B
bz D
1)
0%
09
1-
bz "
bz 5
bz @
bz &
#366740
1'
#368750
0)
#375000
z8
b1 H
b1 I
0=
1)
1%
#381250
b11001100110011000011001100110011 !
b11001100110011000011001100110011 3
b11001100110011000011001100110011 ?
b11001100110011000011001100110011 ;
b11001100110011000011001100110011 C
b110 J
0)
#383410
0'
#387500
b10 H
b10 I
1)
0%
#393750
0)
#400000
b1 H
b0 I
1)
1%
#400080
1'
#406250
0)
#412500
b10 H
b1 I
1)
0%
#415500
0A
11
#416750
0'
#418750
1:
bz !
bz 3
bz ?
b0 ;
b0 C
b1000 J
0)
#425000
b1 H
b10 I
1)
1%
#431250
0)
#433420
1'
#437500
b10 H
b1 I
18
b0 !
b0 3
b0 ?
0B
b11111111111111110000000000000000 D
1)
0%
b11111111111111110000000000000000 "
b11111111111111110000000000000000 5
b11111111111111110000000000000000 @
b11111111111111110000000000000000 &
02
19
0-
#443750
0)
#450000
b1 H
b11 I
1>
1)
1%
#450090
0'
#456250
0)
#462500
1B
08
b10 H
b10 I
b1 <
17
1)
0%
12
#466760
1'
#468750
0)
#475000
b1 H
b1 I
1=
0>
1)
1%
#481250
b11111111111111110000000000000000 !
b11111111111111110000000000000000 3
b11111111111111110000000000000000 ?
b11111111111111110000000000000000 ;
b11111111111111110000000000000000 C
0:
b1010 K
0)
#483430
0'
#484000
1A
01
#487500
b10 H
b10 I
b10 <
b11101110111011100001000100010001 D
b11101110111011100001000100010001 "
b11101110111011100001000100010001 5
b11101110111011100001000100010001 @
b11101110111011100001000100010001 &
1)
0%
#493750
0)
#500000
b1 H
b0 I
1)
1%
#500100
1'
#506250
b1100 K
0)
#512500
b10 H
b1 I
b11 <
b11011101110111010010001000100010 D
1)
0%
b11011101110111010010001000100010 "
b11011101110111010010001000100010 5
b11011101110111010010001000100010 @
b11011101110111010010001000100010 &
#516770
0'
#518750
b11101110111011100001000100010001 !
b11101110111011100001000100010001 3
b11101110111011100001000100010001 ?
b11101110111011100001000100010001 ;
b11101110111011100001000100010001 C
b1010 J
0)
#525000
b1 H
b10 I
1)
1%
#531250
b1110 K
0)
#533440
1'
#537500
b10 H
b1 I
b0 <
b11001100110011000011001100110011 D
1)
0%
b11001100110011000011001100110011 "
b11001100110011000011001100110011 5
b11001100110011000011001100110011 @
b11001100110011000011001100110011 &
#543750
b11011101110111010010001000100010 !
b11011101110111010010001000100010 3
b11011101110111010010001000100010 ?
b11011101110111010010001000100010 ;
b11011101110111010010001000100010 C
b1100 J
0)
#550000
b1 H
b11 I
1)
1%
#550110
0'
#556250
b0 K
0)
#562500
18
b10 H
b10 I
07
0B
bz D
1)
0%
09
1-
bz "
bz 5
bz @
bz &
#566780
1'
#568750
0)
#575000
z8
b1 H
b1 I
0=
1)
1%
#581250
b11001100110011000011001100110011 !
b11001100110011000011001100110011 3
b11001100110011000011001100110011 ?
b11001100110011000011001100110011 ;
b11001100110011000011001100110011 C
b1110 J
0)
#583450
0'
#587500
b10 H
b10 I
1)
0%
#593750
0)
#600000
b1 H
b0 I
1)
1%
#600120
1'
#606250
0)
#612500
b10 H
b1 I
1)
0%
#615500
0A
11
#616790
0'
#618750
1:
bz !
bz 3
bz ?
b0 ;
b0 C
b0 J
0)
#625000
b1 H
b10 I
1)
1%
#631250
0)
#633460
1'
#637500
b10 H
b1 I
1)
0%
#643750
0)
#650000
b1 H
b11 I
1)
1%
#650130
0'
#656250
0)
#662500
b10 H
b10 I
1)
0%
#666800
1'
#668750
0)
#675000
b1 H
b1 I
1)
1%
#681250
0)
#683470
0'
#687500
b10 H
b10 I
1)
0%
#693750
0)
#700000
b1 H
b0 I
1)
1%
#700140
1'
#706250
0)
#712500
b10 H
b1 I
1)
0%
#716810
0'
#718750
0)
#725000
b1 H
b10 I
1)
1%
#731250
0)
#733480
1'
#737500
b10 H
b1 I
1)
0%
#743750
0)
#750000
b1 H
b11 I
1)
1%
#750150
0'
#756250
0)
#762500
b10 H
b10 I
1)
0%
#766820
1'
#768750
0)
#775000
b1 H
b1 I
1)
1%
#781250
0)
#783490
0'
#787500
b10 H
b10 I
1)
0%
#793750
0)
#800000
b1 H
b0 I
1)
1%
#800160
1'
#806250
0)
#812500
b10 H
b1 I
1)
0%
#816830
0'
#818750
0)
#825000
b1 H
b10 I
1)
1%
#831250
0)
#833500
1'
#837500
b10 H
b1 I
1)
0%
#843750
0)
#850000
b1 H
b11 I
1)
1%
#850170
0'
#856250
0)
#862500
b10 H
b10 I
1)
0%
#866840
1'
#868750
0)
#875000
b1 H
b1 I
1)
1%
#881250
0)
#883510
0'
#887500
b10 H
b10 I
1)
0%
#893750
0)
#900000
b1 H
b0 I
1)
1%
#900180
1'
#906250
0)
#912500
b10 H
b1 I
1)
0%
#916850
0'
#918750
0)
#925000
b1 H
b10 I
1)
1%
#931250
0)
#933520
1'
#937500
b10 H
b1 I
1)
0%
#943750
0)
#950000
b1 H
b11 I
1)
1%
#950190
0'
#956250
0)
#962500
b10 H
b10 I
1)
0%
#966860
1'
#968750
0)
#975000
b1 H
b1 I
1)
1%
#981250
0)
#983530
0'
#987500
b10 H
b10 I
1)
0%
#993750
0)
#1000000
b1 H
b0 I
1)
1%
#1000200
1'
#1006250
0)
#1012500
b10 H
b1 I
1)
0%
#1016870
0'
#1018750
0)
#1025000
b1 H
b10 I
1)
1%
#1031250
0)
#1033540
1'
#1037500
b10 H
b1 I
1)
0%
#1043750
0)
#1050000
b1 H
b11 I
1)
1%
#1050210
0'
#1056250
0)
#1062500
b10 H
b10 I
1)
0%
#1066880
1'
#1068750
0)
#1075000
b1 H
b1 I
1)
1%
#1081250
0)
#1083550
0'
#1087500
b10 H
b10 I
1)
0%
#1093750
0)
#1100000
b1 H
b0 I
1)
1%
#1100220
1'
#1106250
0)
#1112500
b10 H
b1 I
1)
0%
#1116890
0'
#1118750
0)
#1125000
b1 H
b10 I
1)
1%
#1131250
0)
#1133560
1'
#1137500
b10 H
b1 I
1)
0%
#1143750
0)
#1150000
b1 H
b11 I
1)
1%
#1150230
0'
#1156250
0)
#1162500
b10 H
b10 I
1)
0%
#1166900
1'
#1168750
0)
#1175000
b1 H
b1 I
1)
1%
#1181250
0)
#1183570
0'
#1187500
b10 H
b10 I
1)
0%
#1193750
0)
#1200000
b1 H
b0 I
1)
1%
#1200240
1'
#1206250
0)
#1212500
b10 H
b1 I
1)
0%
#1216910
0'
#1218750
0)
#1225000
b1 H
b10 I
1)
1%
#1231250
0)
#1233580
1'
#1237500
b10 H
b1 I
1)
0%
#1243750
0)
#1250000
b1 H
b11 I
1)
1%
#1250250
0'
#1256250
0)
#1262500
b10 H
b10 I
1)
0%
#1266920
1'
#1268750
0)
#1275000
b1 H
b1 I
1)
1%
#1281250
0)
#1283590
0'
#1287500
b10 H
b10 I
1)
0%
#1293750
0)
#1300000
b1 H
b0 I
1)
1%
#1300260
1'
#1306250
0)
#1312500
b10 H
b1 I
1)
0%
#1316930
0'
#1318750
0)
#1325000
b1 H
b10 I
1)
1%
#1331250
0)
#1333600
1'
#1337500
b10 H
b1 I
1)
0%
#1343750
0)
#1350000
b1 H
b11 I
1)
1%
#1350270
0'
#1356250
0)
#1362500
b10 H
b10 I
1)
0%
#1366940
1'
#1368750
0)
#1375000
b1 H
b1 I
1)
1%
#1381250
0)
#1383610
0'
#1387500
b10 H
b10 I
1)
0%
#1393750
0)
#1400000
b1 H
b0 I
1)
1%
#1400280
1'
#1406250
0)
#1412500
b10 H
b1 I
1)
0%
#1416950
0'
#1418750
0)
#1425000
b1 H
b10 I
1)
1%
#1431250
0)
#1433620
1'
#1437500
b10 H
b1 I
1)
0%
#1443750
0)
#1450000
b1 H
b11 I
1)
1%
#1450290
0'
#1456250
0)
#1462500
b10 H
b10 I
1)
0%
#1466960
1'
#1468750
0)
#1475000
b1 H
b1 I
1)
1%
#1481250
0)
#1483630
0'
#1487500
b10 H
b10 I
1)
0%
#1493750
0)
#1500000
b1 H
b0 I
1)
1%
#1500300
1'
#1506250
0)
#1512500
b10 H
b1 I
1)
0%
#1516970
0'
#1518750
0)
#1525000
b1 H
b10 I
1)
1%
#1531250
0)
#1533640
1'
#1537500
b10 H
b1 I
1)
0%
#1543750
0)
#1550000
b1 H
b11 I
1)
1%
#1550310
0'
#1556250
0)
#1562500
b10 H
b10 I
1)
0%
#1566980
1'
#1568750
0)
#1575000
b1 H
b1 I
1)
1%
#1581250
0)
#1583650
0'
#1587500
b10 H
b10 I
1)
0%
#1593750
0)
#1600000
b1 H
b0 I
1)
1%
#1600320
1'
#1606250
0)
#1612500
b10 H
b1 I
1)
0%
#1616990
0'
#1618750
0)
#1625000
b1 H
b10 I
1)
1%
#1631250
0)
#1633660
1'
#1637500
b10 H
b1 I
1)
0%
#1643750
0)
#1650000
b1 H
b11 I
1)
1%
#1650330
0'
#1656250
0)
#1662500
b10 H
b10 I
1)
0%
#1667000
1'
#1668750
0)
#1675000
b1 H
b1 I
1)
1%
#1681250
0)
#1683670
0'
#1687500
b10 H
b10 I
1)
0%
#1693750
0)
#1700000
b1 H
b0 I
1)
1%
#1700340
1'
#1706250
0)
#1712500
b10 H
b1 I
1)
0%
#1717010
0'
#1718750
0)
#1725000
b1 H
b10 I
1)
1%
#1731250
0)
#1733680
1'
#1737500
b10 H
b1 I
1)
0%
#1743750
0)
#1750000
b1 H
b11 I
1)
1%
#1750350
0'
#1756250
0)
#1762500
b10 H
b10 I
1)
0%
#1767020
1'
#1768750
0)
#1775000
b1 H
b1 I
1)
1%
#1781250
0)
#1783690
0'
#1787500
b10 H
b10 I
1)
0%
#1793750
0)
#1800000
b1 H
b0 I
1)
1%
#1800360
1'
#1806250
0)
#1812500
b10 H
b1 I
1)
0%
#1817030
0'
#1818750
0)
#1825000
b1 H
b10 I
1)
1%
#1831250
0)
#1833700
1'
#1837500
b10 H
b1 I
1)
0%
#1843750
0)
#1850000
b1 H
b11 I
1)
1%
#1850370
0'
#1856250
0)
#1862500
b10 H
b10 I
1)
0%
#1867040
1'
#1868750
0)
#1875000
b1 H
b1 I
1)
1%
#1881250
0)
#1883710
0'
#1887500
b10 H
b10 I
1)
0%
#1893750
0)
#1900000
b1 H
b0 I
1)
1%
#1900380
1'
#1906250
0)
#1912500
b10 H
b1 I
1)
0%
#1917050
0'
#1918750
0)
#1925000
b1 H
b10 I
1)
1%
#1931250
0)
#1933720
1'
#1937500
b10 H
b1 I
1)
0%
#1943750
0)
#1950000
b1 H
b11 I
1)
1%
#1950390
0'
#1956250
0)
#1962500
b10 H
b10 I
1)
0%
#1967060
1'
#1968750
0)
#1975000
b1 H
b1 I
1)
1%
#1981250
0)
#1983730
0'
#1987500
b10 H
b10 I
1)
0%
#1993750
0)
#2000000
b1 H
b0 I
1)
1%
#2000400
1'
#2006250
0)
#2012500
b10 H
b1 I
1)
0%
#2017070
0'
#2018750
0)
#2025000
b1 H
b10 I
1)
1%
#2031250
0)
#2033740
1'
#2037500
b10 H
b1 I
1)
0%
#2043750
0)
#2050000
b1 H
b11 I
1)
1%
#2050410
0'
#2056250
0)
#2062500
b10 H
b10 I
1)
0%
#2067080
1'
#2068750
0)
#2075000
b1 H
b1 I
1)
1%
#2081250
0)
#2083750
0'
#2087500
b10 H
b10 I
1)
0%
#2093750
0)
#2100000
b1 H
b0 I
1)
1%
#2100420
1'
#2106250
0)
#2112500
b10 H
b1 I
1)
0%
#2117090
0'
#2118750
0)
#2125000
b1 H
b10 I
1)
1%
#2131250
0)
#2133760
1'
#2137500
b10 H
b1 I
1)
0%
#2143750
0)
#2150000
b1 H
b11 I
1)
1%
#2150430
0'
#2156250
0)
#2162500
b10 H
b10 I
1)
0%
#2167100
1'
#2168750
0)
#2175000
b1 H
b1 I
1)
1%
#2181250
0)
#2183770
0'
#2187500
b10 H
b10 I
1)
0%
#2193750
0)
#2200000
b1 H
b0 I
1)
1%
#2200440
1'
#2206250
0)
#2212500
b10 H
b1 I
1)
0%
#2217110
0'
#2218750
0)
#2225000
b1 H
b10 I
1)
1%
#2231250
0)
#2233780
1'
#2237500
b10 H
b1 I
1)
0%
#2243750
0)
#2250000
b1 H
b11 I
1)
1%
#2250450
0'
#2256250
0)
#2262500
b10 H
b10 I
1)
0%
#2267120
1'
#2268750
0)
#2275000
b1 H
b1 I
1)
1%
#2281250
0)
#2283790
0'
#2287500
b10 H
b10 I
1)
0%
#2293750
0)
#2300000
b1 H
b0 I
1)
1%
#2300460
1'
#2306250
0)
#2312500
b10 H
b1 I
1)
0%
#2317130
0'
#2318750
0)
